Workbook
Name SegmentaçãodeDados_ÁREA: #N/A
Name SegmentaçãodeDados_EQUIPE: #N/A
Name SegmentaçãodeDados_MÊS: #N/A

Sheet Mecânica
C33: Disponivel | D33: Pago | E33: %
B34: GERENTE D | C34: 0 | D34: 0 | E34: =IFERROR(D34/C34,) -> 0
B35: GERENTE M | C35: 1400 | D35: 0 | E35: =IFERROR(D35/C35,) -> 0
B36: SUPERVISORES/CONSULTORES | C36: 6500 | D36: 0 | E36: =IFERROR(D36/C36,) -> 0
B37: VENDEDORES/EXECUTIVO | C37: 2500 | D37: 0 | E37: =IFERROR(D37/C37,) -> 0
B38: MERCHANDISING EXTERNO | C38: 0 | D38: 0 | E38: =IFERROR(D38/C39,) -> 0
B39: MERCHANDISING INTERNO | C39: 0 | D39: 0 | E39: =IFERROR(D39/#REF!,) -> 0
B40: TOTAL | C40: =SUM(C33:C39) -> 10400 | D40: =SUM(D33:D39) -> 0 | E40: =IFERROR(D40/C40,) -> 0
C135: Disponível | D135: Pessoas | E135: Disponível TT | F135: Pago | G135: %
B136: GERENTE DE VENDAS | C136: 1500 | D136: 2 | E136: =C136*D136 -> 3000 | F136: 0 | G136: =IFERROR(F136/E136,) -> 0
B137: VENDEDORES VAREJO | C137: 800 | D137: 10 | E137: =C137*D137 -> 8000 | F137: 0 | G137: =IFERROR(F137/E137,) -> 0
B138: VENDEDORES MC/KA | C138: 956 | D138: 9 | E138: =C138*D138 -> 8604 | F138: 0 | G138: =IFERROR(F138/E138,) -> 0
B139: SUPERVISOR VAREJO | C139: 900 | D139: 10 | E139: =C139*D139 -> 9000 | F139: 0 | G139: =IFERROR(F139/E139,) -> 0
B140: SUPERVISOR MC/KA | C140: 550 | D140: 4 | E140: =C140*D140 -> 2200 | F140: 0 | G140: =IFERROR(F140/E140,) -> 0
B141: PROMOTORES | C141: 250 | D141: 30 | E141: =C141*D141 -> 7500 | F141: 0 | G141: =IFERROR(F141/E141,) -> 0
B142: EXTRA | C142: 1300 | D142: 2 | E142: =C142*D142 -> 2600 | F142: 0 | G142: =IFERROR(F142/E142,) -> 0
B143: TOTAL | C143: =SUM(C136:C141) -> 4956 | E143: =SUM(E136:E141) -> 38304 | F143: =SUM(F136:F141) -> 0 | G143: =IFERROR(F143/E143,) -> 0

Sheet ITENS
B4: GRUPO | C4: CÓD | D4: DESCRIÇÃO
B5: LANÇAMENTOS | C5: 125667 | D5: SH PASTA DE AMENDOIM 500 GR POWER CARAMEL SALGADO
B6: LANÇAMENTOS | C6: 125666 | D6: SH PASTA DE AMENDOIM 500 GR POWER ORIGINAL
B7: LANÇAMENTOS | C7: 125572 | D7: SH PASTA AMEN INTEGRAL 500 GR CREAMY
B8: LANÇAMENTOS | C8: 125573 | D8: SH PASTA AMEN INTEGRAL 500 GR CRUNCHY
B9: LANÇAMENTOS | C9: 124628 | D9: PACOQUITA COCO QUEIMADO
B10: LANÇAMENTOS | C10: 125795 | D10: PACOQUITA MAÇA DO AMOR
B11: LANÇAMENTOS | C11: 125794 | D11: PACOQUITA ACUCAR MASCAVO 750
B12: LANÇAMENTOS | C12: 125798 | D12: PACOQUITA ACUCAR MASCAVO 220
B13: LANÇAMENTOS | C13: 125805 | D13: S HELENA MENDORATO 90 GR BACON CA
B14: LANÇAMENTOS | C14: 125807 | D14: S HELENA MENDORATO 90 GR BUFFALO EUA
B15: LANÇAMENTOS | C15: 125804 | D15: S HELENA MENDORATO 90 GR PICANHA BR
B16: LANÇAMENTOS | C16: 125806 | D16: S HELENA MENDORATO 90 GR TACO MX
... B25: PAÇOQUITA ZERO | C25: 88072 | D25: S HELENA PACOQUITA ROLHA 102 G DIET EMB C/6*

Sheet GERAL
E4: ST | F4: (Vários itens)
E6: MÊS | F6: Valores
D7: POSITIVAÇÃO DMULLER | E7: ABRIL | H7: MAIO | K7: JUNHO | N7: JULHO
E8: META | F8: REALIZADO | G8: % P | H8: META | I8: REALIZADO | J8: % P | K8: META | L8: REALIZADO | M8: % P | N8: META | O8: REALIZADO | P8: % P
E9: 3954 | F9: 4269 | G9: 1.0796662 | H9: 4565 | I9: 4604 | J9: 1.0085433 | K9: 4587 | L9: 3041 | M9: 0.66296054 | N9: 4800
E12: MÊS | F12: Valores
D13: FATURAMENTO DMULLER | E13: ABRIL | H13: MAIO | K13: JUNHO | N13: JULHO | Q13: Total META | R13: Total R$ | S13: Total % R$
E14: META | F14: R$ | G14: % R$ | H14: META | I14: R$ | J14: % R$ | K14: META | L14: R$ | M14: % R$ | N14: META | O14: R$ | P14: % R$
E15: 1300000 | F15: 1342212.8 | G15: 1.0324714 | H15: 3600000 | I15: 3046803 | J15: 0.84633418 | K15: 1700000 | L15: 1435479.1 | M15: 0.84439949 | N15: 1600000 | Q15: 8200000 | R15: 5824495 | S15: 0.71030427
D18: 46113 | S18: {=DT_ATT19[Ultima Atualização]} -> 46192.449
D19: =AUX!T103/AUX!S103 -> 0.6557377
D20: PROGRESSO DA CAMPANHA

Sheet AUX
B101: =GERAL!E9 -> 3954 | E101: =GERAL!H9 -> 4565 | H101: =GERAL!K9 -> 4587 | K101: =GERAL!N9 -> 4800 | Q101: Ultima Atualização | T101: =TODAY() -> 46192
B102: REALIZADO | C102: GAP | E102: REALIZADO | F102: GAP | H102: REALIZADO | I102: GAP | K102: REALIZADO | L102: GAP | Q102: 46192.449 | S102: 46113 | T102: 46234
B103: =GERAL!F9 -> 4269 | C103: =IF(B101-Tabela2[[#This Row],[REALIZADO]]<=0,0,B101-Tabela2[[#This Row],[REALIZADO]]) -> 0 | E103: =GERAL!I9 -> 4604 | F103: =IF(E101-Tabela2[[#This Row],[REALIZADO]]<=0,0,E101-Tabela2[[#This Row],[REALIZADO]]) -> 296 | H103: =GERAL!L9 -> 3041 | I103: =IF(H101-Tabela2[[#This Row],[REALIZADO]]<=0,0,H101-Tabela2[[#This Row],[REALIZADO]]) -> 318 | K103: =GERAL!O9 -> 0 | L103: =IF(K101-Tabela2[[#This Row],[REALIZADO]]<=0,0,K101-Tabela2[[#This Row],[REALIZADO]]) -> 531 | S103: =_xlfn.DAYS($T$102,$S$102)+1 -> 122 | T103: =_xlfn.DAYS($T$101,$S$102)+1 -> 80
Q104: ATUALIZAÇÃO
B105: =GERAL!E15 -> 1300000 | E105: =GERAL!H15 -> 3600000 | H105: =GERAL!K15 -> 1700000 | K105: =GERAL!N15 -> 1600000 | N105: =GERAL!Q15 -> 8200000 | Q105: {=DT_ATT[Ultima Atualização]} -> 46192.449
B106: REALIZADO | C106: GAP | E106: REALIZADO | F106: GAP | H106: REALIZADO | I106: GAP | K106: REALIZADO | L106: GAP | N106: REALIZADO | O106: GAP
B107: =GERAL!F15 -> 1342212.8 | C107: =IF(B105-Tabela211[[#This Row],[REALIZADO]]<=0,0,B105-Tabela211[[#This Row],[REALIZADO]]) -> 0 | E107: =GERAL!I15 -> 3046803 | F107: =IF(E105-Tabela512[[#This Row],[REALIZADO]]<=0,0,E105-Tabela512[[#This Row],[REALIZADO]]) -> 553196.95 | H107: =GERAL!L15 -> 1435479.1 | I107: =IF(H105-Tabela815[[#This Row],[REALIZADO]]<=0,0,H105-Tabela815[[#This Row],[REALIZADO]]) -> 264520.87 | K107: =GERAL!O15 -> 0 | L107: =IF(K105-Tabela916[[#This Row],[REALIZADO]]<=0,0,K105-Tabela916[[#This Row],[REALIZADO]]) -> 1600000 | N107: =GERAL!R15 -> 5824495 | O107: =IF(N105-Tabela91617[[#This Row],[REALIZADO]]<=0,0,N105-Tabela91617[[#This Row],[REALIZADO]]) -> 2375505
Q108: Ultima Atualização
Q109: 46192.449

Sheet VAREJO
D3: ST | E3: (Vários itens)
E5: MÊS | F5: Valores | T5: MÊS | U5: Valores
E6: ABRIL | H6: MAIO | K6: JUNHO | N6: JULHO | T6: TOTAL
D7: EQUIPE | E7: META | F7: POSITIVAÇÃO | G7: % P | H7: META | I7: POSITIVAÇÃO | J7: % P | K7: META | L7: POSITIVAÇÃO | M7: % P | N7: META | O7: POSITIVAÇÃO | P7: % P | S7: EQUIPE | T7: META R$ | U7: R$ | V7: % R
D8: FLORIPA M | E8: 654 | F8: 551 | G8: 0.84250765 | H8: 755 | I8: 610 | J8: 0.80794702 | K8: 760 | L8: 414 | M8: 0.54473684 | N8: 0 | S8: FLORIPA M | T8: 261000.08 | U8: 160393.3 | V8: 0.61453353
D9: LITORAL M | E9: 902 | F9: 954 | G9: 1.0576497 | H9: 1040 | I9: 970 | J9: 0.93269231 | K9: 1044 | L9: 671 | M9: 0.64272031 | N9: 0 | S9: LITORAL M | T9: 716500.78 | U9: 530571.11 | V9: 0.74050319
D10: NORTE D | E10: 42 | F10: 20 | G10: 0.47619048 | H10: 48 | I10: 36 | J10: 0.75 | K10: 48 | L10: 28 | M10: 0.58333333 | N10: 0 | S10: NORTE D | T10: 8499.24 | U10: 10556.93 | V10: 1.2421028
D11: NORTE M | E11: 684 | F11: 755 | G11: 1.1038012 | H11: 791 | I11: 831 | J11: 1.0505689 | K11: 792 | L11: 444 | M11: 0.56060606 | N11: 0 | S11: NORTE M | T11: 360500.59 | U11: 328398.95 | V11: 0.9109526
D12: SUL D | E12: 152 | F12: 112 | G12: 0.73684211 | H12: 175 | I12: 115 | J12: 0.65714286 | K12: 177 | L12: 96 | M12: 0.54237288 | N12: 0 | S12: SUL D | T12: 58499.73 | U12: 34730.12 | V12: 0.59368001
D13: SUL M | E13: 768 | F13: 827 | G13: 1.0768229 | H13: 887 | I13: 919 | J13: 1.0360767 | K13: 891 | L13: 509 | M13: 0.57126824 | N13: 0 | S13: SUL M | T13: 234499.41 | U13: 185550.79 | V13: 0.79126336
D14: VALE M | E14: 685 | F14: 634 | G14: 0.92554745 | H14: 792 | I14: 668 | J14: 0.84343434 | K14: 796 | L14: 511 | M14: 0.6419598 | N14: 0 | S14: VALE M | T14: 306997.71 | U14: 274039.8 | V14: 0.89264444
D15: VENDAS INTERNAS | E15: 67 | F15: 142 | G15: 2.119403 | H15: 77 | I15: 156 | J15: 2.025974 | K15: 79 | L15: 136 | M15: 1.721519 | N15: 0 | S15: VENDAS INTERNAS | T15: 86499.88 | U15: 50793.56 | V15: 0.5872096
B16: =COUNTIF(Tabela358[VALIDAÇÃO VENDEDOR],">1") -> 0
B17: =COUNTIF(Tabela35[VALIDAÇÃO VENDEDOR],">1") -> 0
B18: VAREJO M | AJ18: PONTUAÇÕES DO RANKING
B19: GRUPO | C19: VAREJO M
B20: ST | C20: (Vários itens) | R20: GRUPO | S20: VAREJO M | X20: GRUPO | Y20: VAREJO M | AC20: GRUPO | AD20: VAREJO M
X21: ST | Y21: (Vários itens) | AC21: ST | AD21: (Vários itens)
E22: MÊS | F22: Valores | T22: MÊS | U22: Valores
E23: ABRIL | H23: MAIO | K23: JUNHO | N23: JULHO | T23: TOTAL | X23: CONTAGEM ITENS | AC23: POSITIVAÇÃO PAÇOQUITA | AG23: MERCHANDISING | AJ23: PONTUAÇÕES POSITIVAÇÃO | AO23: FATURAMENTO | AQ23: ITENS ESPECIAIS | AT23: MERCHANDISING | AW23: RANKING
B24: EQUIPE | C24: ID | D24: ÁREA | E24: META | F24: POSITIVAÇÃO | G24: % P | H24: META | I24: POSITIVAÇÃO | J24: % P | K24: META | L24: POSITIVAÇÃO | M24: % P | N24: META | O24: POSITIVAÇÃO | P24: % P | R24: EQUIPE | S24: ID | T24: META R$ | U24: R$ | V24: % $ | Z24: LANÇAMENTOS | AA24: PAÇOQUITA ZERO | AE24: PAÇOQUITA ZERO | AG24: BARRACA MONTADA | AH24: PONTO EXTRA | AJ24: POSI ABRIL | AK24: POSI MAIO | AL24: POSI JUNHO | AM24: POSI JULHO | AN24: Coluna1 | AO24: R$ TOTAL | AP24: Coluna12 | AQ24: LANÇAMENTOS | AR24: PAÇOCA ZERO | AS24: Coluna122 | AT24: BARRACAS | AU24: PONTO EXTRA | AV24: Coluna1222 | AW24: TOTAL | AX24: RANKING | AY24: VALIDAÇÃO VENDEDOR
B25: FLORIPA M | C25: 4026 | D25: FLP-CONV-ILHA | E25: 77 | F25: 30 | G25: 0.38961039 | H25: 90 | I25: 49 | J25: 0.54444444 | K25: 90 | L25: 13 | M25: 0.14444444 | N25: 0 | R25: FLORIPA M | S25: 4026 | T25: 29499.61 | U25: 8586.78 | V25: 0.29108114 | X25: FLORIPA M | Y25: 4026 | Z25: 3 | AA25: 39 | AC25: FLORIPA M | AD25: 4026 | AE25: 31 | AG25: =SUMIF(CLIENTES!$C:$C,VAREJO!$C25,CLIENTES!$L:$L) -> 0 | AH25: =SUMIF(CLIENTES!$C:$C,VAREJO!$C25,CLIENTES!$M:$M) -> 0 | AJ25: =IF(G25>=100%,2,0) -> 0 | AK25: =IF(J25>=100%,2,0) -> 0 | AL25: =IF(M25>=100%,2,0) -> 0 | AM25: =IF(P25>=100%,2,0) -> 0 | AO25: =IF($V25>=100%,10,0) -> 0 | AQ25: =AA25 -> 39 | AR25: =$AE25 -> 31 | AT25: =Tabela3[[#This Row],[BARRACA MONTADA]]*5 -> 0 | AU25: =Tabela3[[#This Row],[PONTO EXTRA]]*5 -> 0 | AW25: =SUM(Tabela35[[#This Row],[POSI ABRIL]:[PONTO EXTRA]]) -> 70 | AX25: =_xlfn.RANK.EQ(Tabela35[[#This Row],[TOTAL]],Tabela35[TOTAL],0)& "º" -> 31º | AY25: =COUNTA(_xlfn.UNIQUE(_xlfn.VSTACK(AD25,Y25,S25,C25))) -> 1
C26: 4027 | D26: FLORIPA M | E26: 61 | F26: 67 | G26: 1.0983607 | H26: 71 | I26: 70 | J26: 0.98591549 | K26: 71 | L26: 47 | M26: 0.66197183 | N26: 0 | S26: 4027 | T26: 27000.18 | U26: 17661.98 | V26: 0.65414305 | Y26: 4027 | Z26: 11 | AA26: 45 | AD26: 4027 | AE26: 38 | AG26: =SUMIF(CLIENTES!$C:$C,VAREJO!$C26,CLIENTES!$L:$L) -> 0 | AH26: =SUMIF(CLIENTES!$C:$C,VAREJO!$C26,CLIENTES!$M:$M) -> 0 | AJ26: =IF(G26>=100%,2,0) -> 2 | AK26: =IF(J26>=100%,2,0) -> 0 | AL26: =IF(M26>=100%,2,0) -> 0 | AM26: =IF(P26>=100%,2,0) -> 0 | AO26: =IF($V26>=100%,10,0) -> 0 | AQ26: =AA26 -> 45 | AR26: =$AE26 -> 38 | AT26: =Tabela3[[#This Row],[BARRACA MONTADA]]*5 -> 0 | AU26: =Tabela3[[#This Row],[PONTO EXTRA]]*5 -> 0 | AW26: =SUM(Tabela35[[#This Row],[POSI ABRIL]:[PONTO EXTRA]]) -> 85 | AX26: =_xlfn.RANK.EQ(Tabela35[[#This Row],[TOTAL]],Tabela35[TOTAL],0)& "º" -> 19º | AY26: =COUNTA(_xlfn.UNIQUE(_xlfn.VSTACK(AD26,Y26,S26,C26))) -> 1
C27: 4028 | D27: PALHOCA-SUL M | E27: 73 | F27: 59 | G27: 0.80821918 | H27: 84 | I27: 53 | J27: 0.63095238 | K27: 85 | L27: 41 | M27: 0.48235294 | N27: 0 | S27: 4028 | T27: 22000.33 | U27: 13905.94 | V27: 0.6320787 | Y27: 4028 | Z27: 10 | AA27: 29 | AD27: 4028 | AE27: 24 | AG27: =SUMIF(CLIENTES!$C:$C,VAREJO!$C27,CLIENTES!$L:$L) -> 0 | AH27: =SUMIF(CLIENTES!$C:$C,VAREJO!$C27,CLIENTES!$M:$M) -> 0 | AJ27: =IF(G27>=100%,2,0) -> 0 | AK27: =IF(J27>=100%,2,0) -> 0 | AL27: =IF(M27>=100%,2,0) -> 0 | AM27: =IF(P27>=100%,2,0) -> 0 | AO27: =IF($V27>=100%,10,0) -> 0 | AQ27: =AA27 -> 29 | AR27: =$AE27 -> 24 | AT27: =Tabela3[[#This Row],[BARRACA MONTADA]]*5 -> 0 | AU27: =Tabela3[[#This Row],[PONTO EXTRA]]*5 -> 0 | AW27: =SUM(Tabela35[[#This Row],[POSI ABRIL]:[PONTO EXTRA]]) -> 53 | AX27: =_xlfn.RANK.EQ(Tabela35[[#This Row],[TOTAL]],Tabela35[TOTAL],0)& "º" -> 38º | AY27: =COUNTA(_xlfn.UNIQUE(_xlfn.VSTACK(AD27,Y27,S27,C27))) -> 1
C28: 4029 | D28: FLORIPA-SUL M | E28: 59 | F28: 65 | G28: 1.1016949 | H28: 69 | I28: 76 | J28: 1.1014493 | K28: 69 | L28: 66 | M28: 0.95652174 | N28: 0 | S28: 4029 | T28: 33000 | U28: 25555.06 | V28: 0.77439576 | Y28: 4029 | Z28: 6 | AA28: 60 | AD28: 4029 | AE28: 51 | AG28: =SUMIF(CLIENTES!$C:$C,VAREJO!$C28,CLIENTES!$L:$L) -> 0 | AH28: =SUMIF(CLIENTES!$C:$C,VAREJO!$C28,CLIENTES!$M:$M) -> 0 | AJ28: =IF(G28>=100%,2,0) -> 2 | AK28: =IF(J28>=100%,2,0) -> 2 | AL28: =IF(M28>=100%,2,0) -> 0 | AM28: =IF(P28>=100%,2,0) -> 0 | AO28: =IF($V28>=100%,10,0) -> 0 | AQ28: =AA28 -> 60 | AR28: =$AE28 -> 51 | AT28: =Tabela3[[#This Row],[BARRACA MONTADA]]*5 -> 0 | AU28: =Tabela3[[#This Row],[PONTO EXTRA]]*5 -> 0 | AW28: =SUM(Tabela35[[#This Row],[POSI ABRIL]:[PONTO EXTRA]]) -> 115 | AX28: =_xlfn.RANK.EQ(Tabela35[[#This Row],[TOTAL]],Tabela35[TOTAL],0)& "º" -> 10º | AY28: =COUNTA(_xlfn.UNIQUE(_xlfn.VSTACK(AD28,Y28,S28,C28))) -> 1
C29: 4030 | D29: FLP-CONV-CONT | E29: 71 | F29: 80 | G29: 1.1267606 | H29: 81 | I29: 89 | J29: 1.0987654 | K29: 82 | L29: 60 | M29: 0.73170732 | N29: 0 | S29: 4030 | T29: 33500.48 | U29: 17906.75 | V29: 0.53452219 | Y29: 4030 | Z29: 1 | AA29: 44 | AD29: 4030 | AE29: 40 | AG29: =SUMIF(CLIENTES!$C:$C,VAREJO!$C29,CLIENTES!$L:$L) -> 0 | AH29: =SUMIF(CLIENTES!$C:$C,VAREJO!$C29,CLIENTES!$M:$M) -> 0 | AJ29: =IF(G29>=100%,2,0) -> 2 | AK29: =IF(J29>=100%,2,0) -> 2 | AL29: =IF(M29>=100%,2,0) -> 0 | AM29: =IF(P29>=100%,2,0) -> 0 | AO29: =IF($V29>=100%,10,0) -> 0 | AQ29: =AA29 -> 44 | AR29: =$AE29 -> 40 | AT29: =Tabela3[[#This Row],[BARRACA MONTADA]]*5 -> 0 | AU29: =Tabela3[[#This Row],[PONTO EXTRA]]*5 -> 0 | AW29: =SUM(Tabela35[[#This Row],[POSI ABRIL]:[PONTO EXTRA]]) -> 88 | AX29: =_xlfn.RANK.EQ(Tabela35[[#This Row],[TOTAL]],Tabela35[TOTAL],0)& "º" -> 16º | AY29: =COUNTA(_xlfn.UNIQUE(_xlfn.VSTACK(AD29,Y29,S29,C29))) -> 1
C30: 4038 | D30: FLORIPA-CONT M | E30: 73 | F30: 35 | G30: 0.47945205 | H30: 84 | I30: 39 | J30: 0.46428571 | K30: 85 | L30: 38 | M30: 0.44705882 | N30: 0 | S30: 4038 | T30: 15500.03 | U30: 11676.92 | V30: 0.75334822 | Y30: 4038 | Z30: 4 | AA30: 33 | AD30: 4038 | AE30: 26 | AG30: =SUMIF(CLIENTES!$C:$C,VAREJO!$C30,CLIENTES!$L:$L) -> 0 | AH30: =SUMIF(CLIENTES!$C:$C,VAREJO!$C30,CLIENTES!$M:$M) -> 0 | AJ30: =IF(G30>=100%,2,0) -> 0 | AK30: =IF(J30>=100%,2,0) -> 0 | AL30: =IF(M30>=100%,2,0) -> 0 | AM30: =IF(P30>=100%,2,0) -> 0 | AO30: =IF($V30>=100%,10,0) -> 0 | AQ30: =AA30 -> 33 | AR30: =$AE30 -> 26 | AT30: =Tabela3[[#This Row],[BARRACA MONTADA]]*5 -> 0 | AU30: =Tabela3[[#This Row],[PONTO EXTRA]]*5 -> 0 | AW30: =SUM(Tabela35[[#This Row],[POSI ABRIL]:[PONTO EXTRA]]) -> 59 | AX30: =_xlfn.RANK.EQ(Tabela35[[#This Row],[TOTAL]],Tabela35[TOTAL],0)& "º" -> 36º | AY30: =COUNTA(_xlfn.UNIQUE(_xlfn.VSTACK(AD30,Y30,S30,C30))) -> 1
C31: 4039 | D31: FLORIPA-NORTE M | E31: 56 | F31: 66 | G31: 1.1785714 | H31: 64 | I31: 74 | J31: 1.15625 | K31: 65 | L31: 49 | M31: 0.75384615 | N31: 0 | S31: 4039 | T31: 36999.88 | U31: 17753.26 | V31: 0.47981939 | Y31: 4039 | Z31: 7 | AA31: 51 | AD31: 4039 | AE31: 47 | AG31: =SUMIF(CLIENTES!$C:$C,VAREJO!$C31,CLIENTES!$L:$L) -> 0 | AH31: =SUMIF(CLIENTES!$C:$C,VAREJO!$C31,CLIENTES!$M:$M) -> 0 | AJ31: =IF(G31>=100%,2,0) -> 2 | AK31: =IF(J31>=100%,2,0) -> 2 | AL31: =IF(M31>=100%,2,0) -> 0 | AM31: =IF(P31>=100%,2,0) -> 0 | AO31: =IF($V31>=100%,10,0) -> 0 | AQ31: =AA31 -> 51 | AR31: =$AE31 -> 47 | AT31: =Tabela3[[#This Row],[BARRACA MONTADA]]*5 -> 0 | AU31: =Tabela3[[#This Row],[PONTO EXTRA]]*5 -> 0 | AW31: =SUM(Tabela35[[#This Row],[POSI ABRIL]:[PONTO EXTRA]]) -> 102 | AX31: =_xlfn.RANK.EQ(Tabela35[[#This Row],[TOTAL]],Tabela35[TOTAL],0)& "º" -> 12º | AY31: =COUNTA(_xlfn.UNIQUE(_xlfn.VSTACK(AD31,Y31,S31,C31))) -> 1
C32: 4040 | D32: BIGUACU M | E32: 63 | F32: 54 | G32: 0.85714286 | H32: 73 | I32: 82 | J32: 1.1232877 | K32: 73 | L32: 37 | M32: 0.50684932 | N32: 0 | S32: 4040 | T32: 18499.94 | U32: 19194.6 | V32: 1.0375493 | Y32: 4040 | Z32: 20 | AA32: 40 | AD32: 4040 | AE32: 31 | AG32: =SUMIF(CLIENTES!$C:$C,VAREJO!$C32,CLIENTES!$L:$L) -> 1 | AH32: =SUMIF(CLIENTES!$C:$C,VAREJO!$C32,CLIENTES!$M:$M) -> 0 | AJ32: =IF(G32>=100%,2,0) -> 0 | AK32: =IF(J32>=100%,2,0) -> 2 | AL32: =IF(M32>=100%,2,0) -> 0 | AM32: =IF(P32>=100%,2,0) -> 0 | AO32: =IF($V32>=100%,10,0) -> 10 | AQ32: =AA32 -> 40 | AR32: =$AE32 -> 31 | AT32: =Tabela3[[#This Row],[BARRACA MONTADA]]*5 -> 5 | AU32: =Tabela3[[#This Row],[PONTO EXTRA]]*5 -> 0 | AW32: =SUM(Tabela35[[#This Row],[POSI ABRIL]:[PONTO EXTRA]]) -> 88 | AX32: =_xlfn.RANK.EQ(Tabela35[[#This Row],[TOTAL]],Tabela35[TOTAL],0)& "º" -> 16º | AY32: =COUNTA(_xlfn.UNIQUE(_xlfn.VSTACK(AD32,Y32,S32,C32))) -> 1
C33: 4071 | D33: SAO JOSE M | E33: 66 | F33: 31 | G33: 0.46969697 | H33: 76 | I33: 11 | J33: 0.14473684 | K33: 76 | L33: 5 | M33: 0.065789474 | N33: 0 | S33: 4071 | T33: 24999.24 | U33: 4337.87 | V33: 0.17352008 | Y33: 4071 | AA33: 8 | AD33: 4071 | AE33: 6 | AG33: =SUMIF(CLIENTES!$C:$C,VAREJO!$C33,CLIENTES!$L:$L) -> 0 | AH33: =SUMIF(CLIENTES!$C:$C,VAREJO!$C33,CLIENTES!$M:$M) -> 0 | AJ33: =IF(G33>=100%,2,0) -> 0 | AK33: =IF(J33>=100%,2,0) -> 0 | AL33: =IF(M33>=100%,2,0) -> 0 | AM33: =IF(P33>=100%,2,0) -> 0 | AO33: =IF($V33>=100%,10,0) -> 0 | AQ33: =AA33 -> 8 | AR33: =$AE33 -> 6 | AT33: =Tabela3[[#This Row],[BARRACA MONTADA]]*5 -> 0 | AU33: =Tabela3[[#This Row],[PONTO EXTRA]]*5 -> 0 | AW33: =SUM(Tabela35[[#This Row],[POSI ABRIL]:[PONTO EXTRA]]) -> 14 | AX33: =_xlfn.RANK.EQ(Tabela35[[#This Row],[TOTAL]],Tabela35[TOTAL],0)& "º" -> 53º | AY33: =COUNTA(_xlfn.UNIQUE(_xlfn.VSTACK(AD33,Y33,S33,C33))) -> 1
C34: 4072 | D34: STO AMARO M | E34: 55 | F34: 60 | G34: 1.0909091 | H34: 63 | I34: 64 | J34: 1.015873 | K34: 64 | L34: 38 | M34: 0.59375 | N34: 0 | S34: 4072 | T34: 20000.39 | U34: 18021.88 | V34: 0.90107643 | Y34: 4072 | Z34: 1 | AA34: 36 | AD34: 4072 | AE34: 28 | AG34: =SUMIF(CLIENTES!$C:$C,VAREJO!$C34,CLIENTES!$L:$L) -> 1 | AH34: =SUMIF(CLIENTES!$C:$C,VAREJO!$C34,CLIENTES!$M:$M) -> 0 | AJ34: =IF(G34>=100%,2,0) -> 2 | AK34: =IF(J34>=100%,2,0) -> 2 | AL34: =IF(M34>=100%,2,0) -> 0 | AM34: =IF(P34>=100%,2,0) -> 0 | AO34: =IF($V34>=100%,10,0) -> 0 | AQ34: =AA34 -> 36 | AR34: =$AE34 -> 28 | AT34: =Tabela3[[#This Row],[BARRACA MONTADA]]*5 -> 5 | AU34: =Tabela3[[#This Row],[PONTO EXTRA]]*5 -> 0 | AW34: =SUM(Tabela35[[#This Row],[POSI ABRIL]:[PONTO EXTRA]]) -> 73 | AX34: =_xlfn.RANK.EQ(Tabela35[[#This Row],[TOTAL]],Tabela35[TOTAL],0)& "º" -> 29º | AY34: =COUNTA(_xlfn.UNIQUE(_xlfn.VSTACK(AD34,Y34,S34,C34))) -> 1
B35: LITORAL M | C35: 3988 | D35: BCA M | E35: 97 | F35: 88 | G35: 0.90721649 | H35: 112 | I35: 85 | J35: 0.75892857 | K35: 112 | L35: 67 | M35: 0.59821429 | N35: 0 | R35: LITORAL M | S35: 3988 | T35: 180999.52 | U35: 117746.37 | V35: 0.65053416 | X35: LITORAL M | Y35: 3988 | Z35: 24 | AA35: 72 | AC35: LITORAL M | AD35: 3988 | AE35: 48 | AG35: =SUMIF(CLIENTES!$C:$C,VAREJO!$C35,CLIENTES!$L:$L) -> 1 | AH35: =SUMIF(CLIENTES!$C:$C,VAREJO!$C35,CLIENTES!$M:$M) -> 1 | AJ35: =IF(G35>=100%,2,0) -> 0 | AK35: =IF(J35>=100%,2,0) -> 0 | AL35: =IF(M35>=100%,2,0) -> 0 | AM35: =IF(P35>=100%,2,0) -> 0 | AO35: =IF($V35>=100%,10,0) -> 0 | AQ35: =AA35 -> 72 | AR35: =$AE35 -> 48 | AT35: =Tabela3[[#This Row],[BARRACA MONTADA]]*5 -> 5 | AU35: =Tabela3[[#This Row],[PONTO EXTRA]]*5 -> 5 | AW35: =SUM(Tabela35[[#This Row],[POSI ABRIL]:[PONTO EXTRA]]) -> 130 | AX35: =_xlfn.RANK.EQ(Tabela35[[#This Row],[TOTAL]],Tabela35[TOTAL],0)& "º" -> 5º | AY35: =COUNTA(_xlfn.UNIQUE(_xlfn.VSTACK(AD35,Y35,S35,C35))) -> 1
C36: 3989 | D36: PICARRAS M | E36: 89 | F36: 104 | G36: 1.1685393 | H36: 102 | I36: 110 | J36: 1.0784314 | K36: 103 | L36: 77 | M36: 0.74757282 | N36: 0 | S36: 3989 | T36: 85499.91 | U36: 59594.73 | V36: 0.69701512 | Y36: 3989 | Z36: 34 | AA36: 42 | AD36: 3989 | AE36: 38 | AG36: =SUMIF(CLIENTES!$C:$C,VAREJO!$C36,CLIENTES!$L:$L) -> 5 | AH36: =SUMIF(CLIENTES!$C:$C,VAREJO!$C36,CLIENTES!$M:$M) -> 0 | AJ36: =IF(G36>=100%,2,0) -> 2 | AK36: =IF(J36>=100%,2,0) -> 2 | AL36: =IF(M36>=100%,2,0) -> 0 | AM36: =IF(P36>=100%,2,0) -> 0 | AO36: =IF($V36>=100%,10,0) -> 0 | AQ36: =AA36 -> 42 | AR36: =$AE36 -> 38 | AT36: =Tabela3[[#This Row],[BARRACA MONTADA]]*5 -> 25 | AU36: =Tabela3[[#This Row],[PONTO EXTRA]]*5 -> 0 | AW36: =SUM(Tabela35[[#This Row],[POSI ABRIL]:[PONTO EXTRA]]) -> 109 | AX36: =_xlfn.RANK.EQ(Tabela35[[#This Row],[TOTAL]],Tabela35[TOTAL],0)& "º" -> 11º | AY36: =COUNTA(_xlfn.UNIQUE(_xlfn.VSTACK(AD36,Y36,S36,C36))) -> 1
C37: 3990 | D37: TIJUCAS M | E37: 82 | F37: 93 | G37: 1.1341463 | H37: 95 | I37: 104 | J37: 1.0947368 | K37: 95 | L37: 60 | M37: 0.63157895 | N37: 0 | S37: 3990 | T37: 43000.7 | U37: 34754.52 | V37: 0.80823149 | Y37: 3990 | Z37: 32 | AA37: 45 | AD37: 3990 | AE37: 34 | AG37: =SUMIF(CLIENTES!$C:$C,VAREJO!$C37,CLIENTES!$L:$L) -> 1 | AH37: =SUMIF(CLIENTES!$C:$C,VAREJO!$C37,CLIENTES!$M:$M) -> 0 | AJ37: =IF(G37>=100%,2,0) -> 2 | AK37: =IF(J37>=100%,2,0) -> 2 | AL37: =IF(M37>=100%,2,0) -> 0 | AM37: =IF(P37>=100%,2,0) -> 0 | AO37: =IF($V37>=100%,10,0) -> 0 | AQ37: =AA37 -> 45 | AR37: =$AE37 -> 34 | AT37: =Tabela3[[#This Row],[BARRACA MONTADA]]*5 -> 5 | AU37: =Tabela3[[#This Row],[PONTO EXTRA]]*5 -> 0 | AW37: =SUM(Tabela35[[#This Row],[POSI ABRIL]:[PONTO EXTRA]]) -> 88 | AX37: =_xlfn.RANK.EQ(Tabela35[[#This Row],[TOTAL]],Tabela35[TOTAL],0)& "º" -> 16º | AY37: =COUNTA(_xlfn.UNIQUE(_xlfn.VSTACK(AD37,Y37,S37,C37))) -> 1
C38: 3995 | D38: CAMBORIU M | E38: 75 | F38: 81 | G38: 1.08 | H38: 87 | I38: 71 | J38: 0.81609195 | K38: 87 | L38: 26 | M38: 0.29885057 | N38: 0 | S38: 3995 | T38: 33999.97 | U38: 24104.33 | V38: 0.70895151 | Y38: 3995 | Z38: 26 | AA38: 37 | AD38: 3995 | AE38: 26 | AG38: =SUMIF(CLIENTES!$C:$C,VAREJO!$C38,CLIENTES!$L:$L) -> 0 | AH38: =SUMIF(CLIENTES!$C:$C,VAREJO!$C38,CLIENTES!$M:$M) -> 0 | AJ38: =IF(G38>=100%,2,0) -> 2 | AK38: =IF(J38>=100%,2,0) -> 0 | AL38: =IF(M38>=100%,2,0) -> 0 | AM38: =IF(P38>=100%,2,0) -> 0 | AO38: =IF($V38>=100%,10,0) -> 0 | AQ38: =AA38 -> 37 | AR38: =$AE38 -> 26 | AT38: =Tabela3[[#This Row],[BARRACA MONTADA]]*5 -> 0 | AU38: =Tabela3[[#This Row],[PONTO EXTRA]]*5 -> 0 | AW38: =SUM(Tabela35[[#This Row],[POSI ABRIL]:[PONTO EXTRA]]) -> 65 | AX38: =_xlfn.RANK.EQ(Tabela35[[#This Row],[TOTAL]],Tabela35[TOTAL],0)& "º" -> 33º | AY38: =COUNTA(_xlfn.UNIQUE(_xlfn.VSTACK(AD38,Y38,S38,C38))) -> 1
C39: 3997 | D39: BRUSQUE M | E39: 90 | F39: 82 | G39: 0.91111111 | H39: 103 | I39: 105 | J39: 1.0194175 | K39: 104 | L39: 70 | M39: 0.67307692 | N39: 0 | S39: 3997 | T39: 71500.33 | U39: 68560.54 | V39: 0.95888425 | Y39: 3997 | Z39: 16 | AA39: 33 | AD39: 3997 | AE39: 27 | AG39: =SUMIF(CLIENTES!$C:$C,VAREJO!$C39,CLIENTES!$L:$L) -> 3 | AH39: =SUMIF(CLIENTES!$C:$C,VAREJO!$C39,CLIENTES!$M:$M) -> 0 | AJ39: =IF(G39>=100%,2,0) -> 0 | AK39: =IF(J39>=100%,2,0) -> 2 | AL39: =IF(M39>=100%,2,0) -> 0 | AM39: =IF(P39>=100%,2,0) -> 0 | AO39: =IF($V39>=100%,10,0) -> 0 | AQ39: =AA39 -> 33 | AR39: =$AE39 -> 27 | AT39: =Tabela3[[#This Row],[BARRACA MONTADA]]*5 -> 15 | AU39: =Tabela3[[#This Row],[PONTO EXTRA]]*5 -> 0 | AW39: =SUM(Tabela35[[#This Row],[POSI ABRIL]:[PONTO EXTRA]]) -> 77 | AX39: =_xlfn.RANK.EQ(Tabela35[[#This Row],[TOTAL]],Tabela35[TOTAL],0)& "º" -> 25º | AY39: =COUNTA(_xlfn.UNIQUE(_xlfn.VSTACK(AD39,Y39,S39,C39))) -> 1
C40: 3999 | D40: NAVEGANTES M | E40: 70 | F40: 73 | G40: 1.0428571 | H40: 80 | I40: 74 | J40: 0.925 | K40: 81 | L40: 53 | M40: 0.65432099 | N40: 0 | S40: 3999 | T40: 26000.21 | U40: 16690.35 | V40: 0.64193135 | Y40: 3999 | Z40: 18 | AA40: 18 | AD40: 3999 | AE40: 16 | AG40: =SUMIF(CLIENTES!$C:$C,VAREJO!$C40,CLIENTES!$L:$L) -> 0 | AH40: =SUMIF(CLIENTES!$C:$C,VAREJO!$C40,CLIENTES!$M:$M) -> 0 | AJ40: =IF(G40>=100%,2,0) -> 2 | AK40: =IF(J40>=100%,2,0) -> 0 | AL40: =IF(M40>=100%,2,0) -> 0 | AM40: =IF(P40>=100%,2,0) -> 0 | AO40: =IF($V40>=100%,10,0) -> 0 | AQ40: =AA40 -> 18 | AR40: =$AE40 -> 16 | AT40: =Tabela3[[#This Row],[BARRACA MONTADA]]*5 -> 0 | AU40: =Tabela3[[#This Row],[PONTO EXTRA]]*5 -> 0 | AW40: =SUM(Tabela35[[#This Row],[POSI ABRIL]:[PONTO EXTRA]]) -> 36 | AX40: =_xlfn.RANK.EQ(Tabela35[[#This Row],[TOTAL]],Tabela35[TOTAL],0)& "º" -> 47º | AY40: =COUNTA(_xlfn.UNIQUE(_xlfn.VSTACK(AD40,Y40,S40,C40))) -> 1
C41: 4000 | D41: BCA CONV | E41: 67 | F41: 80 | G41: 1.1940299 | H41: 77 | I41: 85 | J41: 1.1038961 | K41: 77 | L41: 66 | M41: 0.85714286 | N41: 0 | S41: 4000 | T41: 68500.42 | U41: 48009.7 | V41: 0.70086724 | Y41: 4000 | Z41: 35 | AA41: 65 | AD41: 4000 | AE41: 47 | AG41: =SUMIF(CLIENTES!$C:$C,VAREJO!$C41,CLIENTES!$L:$L) -> 4 | AH41: =SUMIF(CLIENTES!$C:$C,VAREJO!$C41,CLIENTES!$M:$M) -> 0 | AJ41: =IF(G41>=100%,2,0) -> 2 | AK41: =IF(J41>=100%,2,0) -> 2 | AL41: =IF(M41>=100%,2,0) -> 0 | AM41: =IF(P41>=100%,2,0) -> 0 | AO41: =IF($V41>=100%,10,0) -> 0 | AQ41: =AA41 -> 65 | AR41: =$AE41 -> 47 | AT41: =Tabela3[[#This Row],[BARRACA MONTADA]]*5 -> 20 | AU41: =Tabela3[[#This Row],[PONTO EXTRA]]*5 -> 0 | AW41: =SUM(Tabela35[[#This Row],[POSI ABRIL]:[PONTO EXTRA]]) -> 136 | AX41: =_xlfn.RANK.EQ(Tabela35[[#This Row],[TOTAL]],Tabela35[TOTAL],0)& "º" -> 1º | AY41: =COUNTA(_xlfn.UNIQUE(_xlfn.VSTACK(AD41,Y41,S41,C41))) -> 1
C42: 4001 | D42: ITAJAI-NORTE M | E42: 58 | F42: 66 | G42: 1.137931 | H42: 67 | I42: 69 | J42: 1.0298507 | K42: 67 | L42: 44 | M42: 0.65671642 | N42: 0 | S42: 4001 | T42: 31500.55 | U42: 26286.27 | V42: 0.83447019 | Y42: 4001 | Z42: 14 | AA42: 49 | AD42: 4001 | AE42: 39 | AG42: =SUMIF(CLIENTES!$C:$C,VAREJO!$C42,CLIENTES!$L:$L) -> 7 | AH42: =SUMIF(CLIENTES!$C:$C,VAREJO!$C42,CLIENTES!$M:$M) -> 0 | AJ42: =IF(G42>=100%,2,0) -> 2 | AK42: =IF(J42>=100%,2,0) -> 2 | AL42: =IF(M42>=100%,2,0) -> 0 | AM42: =IF(P42>=100%,2,0) -> 0 | AO42: =IF($V42>=100%,10,0) -> 0 | AQ42: =AA42 -> 49 | AR42: =$AE42 -> 39 | AT42: =Tabela3[[#This Row],[BARRACA MONTADA]]*5 -> 35 | AU42: =Tabela3[[#This Row],[PONTO EXTRA]]*5 -> 0 | AW42: =SUM(Tabela35[[#This Row],[POSI ABRIL]:[PONTO EXTRA]]) -> 127 | AX42: =_xlfn.RANK.EQ(Tabela35[[#This Row],[TOTAL]],Tabela35[TOTAL],0)& "º" -> 6º | AY42: =COUNTA(_xlfn.UNIQUE(_xlfn.VSTACK(AD42,Y42,S42,C42))) -> 1
C43: 4024 | D43: ITAJAI CONV | E43: 67 | F43: 68 | G43: 1.0149254 | H43: 77 | I43: 57 | J43: 0.74025974 | K43: 77 | L43: 62 | M43: 0.80519481 | N43: 0 | S43: 4024 | T43: 53000.39 | U43: 31186.69 | V43: 0.58842378 | Y43: 4024 | Z43: 4 | AA43: 43 | AD43: 4024 | AE43: 39 | AG43: =SUMIF(CLIENTES!$C:$C,VAREJO!$C43,CLIENTES!$L:$L) -> 1 | AH43: =SUMIF(CLIENTES!$C:$C,VAREJO!$C43,CLIENTES!$M:$M) -> 0 | AJ43: =IF(G43>=100%,2,0) -> 2 | AK43: =IF(J43>=100%,2,0) -> 0 | AL43: =IF(M43>=100%,2,0) -> 0 | AM43: =IF(P43>=100%,2,0) -> 0 | AO43: =IF($V43>=100%,10,0) -> 0 | AQ43: =AA43 -> 43 | AR43: =$AE43 -> 39 | AT43: =Tabela3[[#This Row],[BARRACA MONTADA]]*5 -> 5 | AU43: =Tabela3[[#This Row],[PONTO EXTRA]]*5 -> 0 | AW43: =SUM(Tabela35[[#This Row],[POSI ABRIL]:[PONTO EXTRA]]) -> 89 | AX43: =_xlfn.RANK.EQ(Tabela35[[#This Row],[TOTAL]],Tabela35[TOTAL],0)& "º" -> 15º | AY43: =COUNTA(_xlfn.UNIQUE(_xlfn.VSTACK(AD43,Y43,S43,C43))) -> 1
C44: 4048 | D44: ITAPEMA M | E44: 63 | F44: 80 | G44: 1.2698413 | H44: 73 | I44: 75 | J44: 1.0273973 | K44: 73 | L44: 59 | M44: 0.80821918 | N44: 0 | S44: 4048 | T44: 39499.3 | U44: 36886.83 | V44: 0.93386035 | Y44: 4048 | Z44: 40 | AA44: 53 | AD44: 4048 | AE44: 49 | AG44: =SUMIF(CLIENTES!$C:$C,VAREJO!$C44,CLIENTES!$L:$L) -> 5 | AH44: =SUMIF(CLIENTES!$C:$C,VAREJO!$C44,CLIENTES!$M:$M) -> 0 | AJ44: =IF(G44>=100%,2,0) -> 2 | AK44: =IF(J44>=100%,2,0) -> 2 | AL44: =IF(M44>=100%,2,0) -> 0 | AM44: =IF(P44>=100%,2,0) -> 0 | AO44: =IF($V44>=100%,10,0) -> 0 | AQ44: =AA44 -> 53 | AR44: =$AE44 -> 49 | AT44: =Tabela3[[#This Row],[BARRACA MONTADA]]*5 -> 25 | AU44: =Tabela3[[#This Row],[PONTO EXTRA]]*5 -> 0 | AW44: =SUM(Tabela35[[#This Row],[POSI ABRIL]:[PONTO EXTRA]]) -> 131 | AX44: =_xlfn.RANK.EQ(Tabela35[[#This Row],[TOTAL]],Tabela35[TOTAL],0)& "º" -> 3º | AY44: =COUNTA(_xlfn.UNIQUE(_xlfn.VSTACK(AD44,Y44,S44,C44))) -> 1
C45: 4049 | D45: LUIZ ALVES M | E45: 60 | F45: 65 | G45: 1.0833333 | H45: 70 | I45: 71 | J45: 1.0142857 | K45: 70 | L45: 39 | M45: 0.55714286 | N45: 0 | S45: 4049 | T45: 39499.3 | U45: 36948.54 | V45: 0.93542265 | Y45: 4049 | Z45: 7 | AA45: 36 | AD45: 4049 | AE45: 29 | AG45: =SUMIF(CLIENTES!$C:$C,VAREJO!$C45,CLIENTES!$L:$L) -> 3 | AH45: =SUMIF(CLIENTES!$C:$C,VAREJO!$C45,CLIENTES!$M:$M) -> 0 | AJ45: =IF(G45>=100%,2,0) -> 2 | AK45: =IF(J45>=100%,2,0) -> 2 | AL45: =IF(M45>=100%,2,0) -> 0 | AM45: =IF(P45>=100%,2,0) -> 0 | AO45: =IF($V45>=100%,10,0) -> 0 | AQ45: =AA45 -> 36 | AR45: =$AE45 -> 29 | AT45: =Tabela3[[#This Row],[BARRACA MONTADA]]*5 -> 15 | AU45: =Tabela3[[#This Row],[PONTO EXTRA]]*5 -> 0 | AW45: =SUM(Tabela35[[#This Row],[POSI ABRIL]:[PONTO EXTRA]]) -> 84 | AX45: =_xlfn.RANK.EQ(Tabela35[[#This Row],[TOTAL]],Tabela35[TOTAL],0)& "º" -> 22º | AY45: =COUNTA(_xlfn.UNIQUE(_xlfn.VSTACK(AD45,Y45,S45,C45))) -> 1
C46: 4051 | D46: ITAJAI-SUL M | E46: 84 | F46: 74 | G46: 0.88095238 | H46: 97 | I46: 64 | J46: 0.65979381 | K46: 98 | L46: 49 | M46: 0.5 | N46: 0 | S46: 4051 | T46: 43500.18 | U46: 29802.24 | V46: 0.68510613 | Y46: 4051 | Z46: 25 | AA46: 41 | AD46: 4051 | AE46: 33 | AG46: =SUMIF(CLIENTES!$C:$C,VAREJO!$C46,CLIENTES!$L:$L) -> 1 | AH46: =SUMIF(CLIENTES!$C:$C,VAREJO!$C46,CLIENTES!$M:$M) -> 0 | AJ46: =IF(G46>=100%,2,0) -> 0 | AK46: =IF(J46>=100%,2,0) -> 0 | AL46: =IF(M46>=100%,2,0) -> 0 | AM46: =IF(P46>=100%,2,0) -> 0 | AO46: =IF($V46>=100%,10,0) -> 0 | AQ46: =AA46 -> 41 | AR46: =$AE46 -> 33 | AT46: =Tabela3[[#This Row],[BARRACA MONTADA]]*5 -> 5 | AU46: =Tabela3[[#This Row],[PONTO EXTRA]]*5 -> 0 | AW46: =SUM(Tabela35[[#This Row],[POSI ABRIL]:[PONTO EXTRA]]) -> 79 | AX46: =_xlfn.RANK.EQ(Tabela35[[#This Row],[TOTAL]],Tabela35[TOTAL],0)& "º" -> 24º | AY46: =COUNTA(_xlfn.UNIQUE(_xlfn.VSTACK(AD46,Y46,S46,C46))) -> 1
B47: NORTE M | C47: 3970 | D47: ARAQUARI M | E47: 73 | F47: 84 | G47: 1.1506849 | H47: 84 | I47: 89 | J47: 1.0595238 | K47: 85 | L47: 49 | M47: 0.57647059 | N47: 0 | R47: NORTE M | S47: 3970 | T47: 51499.94 | U47: 37159.34 | V47: 0.72154142 | X47: NORTE M | Y47: 3970 | Z47: 48 | AA47: 40 | AC47: NORTE M | AD47: 3970 | AE47: 31 | AG47: =SUMIF(CLIENTES!$C:$C,VAREJO!$C47,CLIENTES!$L:$L) -> 2 | AH47: =SUMIF(CLIENTES!$C:$C,VAREJO!$C47,CLIENTES!$M:$M) -> 0 | AJ47: =IF(G47>=100%,2,0) -> 2 | AK47: =IF(J47>=100%,2,0) -> 2 | AL47: =IF(M47>=100%,2,0) -> 0 | AM47: =IF(P47>=100%,2,0) -> 0 | AO47: =IF($V47>=100%,10,0) -> 0 | AQ47: =AA47 -> 40 | AR47: =$AE47 -> 31 | AT47: =Tabela3[[#This Row],[BARRACA MONTADA]]*5 -> 10 | AU47: =Tabela3[[#This Row],[PONTO EXTRA]]*5 -> 0 | AW47: =SUM(Tabela35[[#This Row],[POSI ABRIL]:[PONTO EXTRA]]) -> 85 | AX47: =_xlfn.RANK.EQ(Tabela35[[#This Row],[TOTAL]],Tabela35[TOTAL],0)& "º" -> 19º | AY47: =COUNTA(_xlfn.UNIQUE(_xlfn.VSTACK(AD47,Y47,S47,C47))) -> 1
C48: 3972 | D48: JARAGUA M | E48: 66 | F48: 79 | G48: 1.1969697 | H48: 76 | I48: 88 | J48: 1.1578947 | K48: 76 | L48: 60 | M48: 0.78947368 | N48: 0 | S48: 3972 | T48: 64500.55 | U48: 62467.27 | V48: 0.96847655 | Y48: 3972 | Z48: 16 | AA48: 27 | AD48: 3972 | AE48: 21 | AG48: =SUMIF(CLIENTES!$C:$C,VAREJO!$C48,CLIENTES!$L:$L) -> 16 | AH48: =SUMIF(CLIENTES!$C:$C,VAREJO!$C48,CLIENTES!$M:$M) -> 0 | AJ48: =IF(G48>=100%,2,0) -> 2 | AK48: =IF(J48>=100%,2,0) -> 2 | AL48: =IF(M48>=100%,2,0) -> 0 | AM48: =IF(P48>=100%,2,0) -> 0 | AO48: =IF($V48>=100%,10,0) -> 0 | AQ48: =AA48 -> 27 | AR48: =$AE48 -> 21 | AT48: =Tabela3[[#This Row],[BARRACA MONTADA]]*5 -> 80 | AU48: =Tabela3[[#This Row],[PONTO EXTRA]]*5 -> 0 | AW48: =SUM(Tabela35[[#This Row],[POSI ABRIL]:[PONTO EXTRA]]) -> 132 | AX48: =_xlfn.RANK.EQ(Tabela35[[#This Row],[TOTAL]],Tabela35[TOTAL],0)& "º" -> 2º | AY48: =COUNTA(_xlfn.UNIQUE(_xlfn.VSTACK(AD48,Y48,S48,C48))) -> 1
C49: 3974 | D49: JOINVILLE M | E49: 43 | F49: 50 | G49: 1.1627907 | H49: 50 | I49: 50 | J49: 1 | K49: 50 | L49: 37 | M49: 0.74 | N49: 0 | S49: 3974 | T49: 12500.12 | U49: 11865.16 | V49: 0.94920369 | Y49: 3974 | Z49: 9 | AA49: 28 | AD49: 3974 | AE49: 24 | AG49: =SUMIF(CLIENTES!$C:$C,VAREJO!$C49,CLIENTES!$L:$L) -> 1 | AH49: =SUMIF(CLIENTES!$C:$C,VAREJO!$C49,CLIENTES!$M:$M) -> 0 | AJ49: =IF(G49>=100%,2,0) -> 2 | AK49: =IF(J49>=100%,2,0) -> 2 | AL49: =IF(M49>=100%,2,0) -> 0 | AM49: =IF(P49>=100%,2,0) -> 0 | AO49: =IF($V49>=100%,10,0) -> 0 | AQ49: =AA49 -> 28 | AR49: =$AE49 -> 24 | AT49: =Tabela3[[#This Row],[BARRACA MONTADA]]*5 -> 5 | AU49: =Tabela3[[#This Row],[PONTO EXTRA]]*5 -> 0 | AW49: =SUM(Tabela35[[#This Row],[POSI ABRIL]:[PONTO EXTRA]]) -> 61 | AX49: =_xlfn.RANK.EQ(Tabela35[[#This Row],[TOTAL]],Tabela35[TOTAL],0)& "º" -> 34º | AY49: =COUNTA(_xlfn.UNIQUE(_xlfn.VSTACK(AD49,Y49,S49,C49))) -> 1
C50: 3975 | D50: JLLE-NORTE M | E50: 63 | F50: 71 | G50: 1.1269841 | H50: 73 | I50: 79 | J50: 1.0821918 | K50: 73 | L50: 61 | M50: 0.83561644 | N50: 0 | S50: 3975 | T50: 30499.58 | U50: 31728.72 | V50: 1.0403002 | Y50: 3975 | Z50: 23 | AA50: 59 | AD50: 3975 | AE50: 41 | AG50: =SUMIF(CLIENTES!$C:$C,VAREJO!$C50,CLIENTES!$L:$L) -> 1 | AH50: =SUMIF(CLIENTES!$C:$C,VAREJO!$C50,CLIENTES!$M:$M) -> 0 | AJ50: =IF(G50>=100%,2,0) -> 2 | AK50: =IF(J50>=100%,2,0) -> 2 | AL50: =IF(M50>=100%,2,0) -> 0 | AM50: =IF(P50>=100%,2,0) -> 0 | AO50: =IF($V50>=100%,10,0) -> 10 | AQ50: =AA50 -> 59 | AR50: =$AE50 -> 41 | AT50: =Tabela3[[#This Row],[BARRACA MONTADA]]*5 -> 5 | AU50: =Tabela3[[#This Row],[PONTO EXTRA]]*5 -> 0 | AW50: =SUM(Tabela35[[#This Row],[POSI ABRIL]:[PONTO EXTRA]]) -> 119 | AX50: =_xlfn.RANK.EQ(Tabela35[[#This Row],[TOTAL]],Tabela35[TOTAL],0)& "º" -> 9º | AY50: =COUNTA(_xlfn.UNIQUE(_xlfn.VSTACK(AD50,Y50,S50,C50))) -> 1
C51: 3976 | D51: JLLE-LESTE M | E51: 58 | F51: 75 | G51: 1.2931034 | H51: 67 | I51: 68 | J51: 1.0149254 | K51: 67 | L51: 40 | M51: 0.59701493 | N51: 0 | S51: 3976 | T51: 16500 | U51: 11614.9 | V51: 0.70393333 | Y51: 3976 | Z51: 38 | AA51: 15 | AD51: 3976 | AE51: 14 | AG51: =SUMIF(CLIENTES!$C:$C,VAREJO!$C51,CLIENTES!$L:$L) -> 0 | AH51: =SUMIF(CLIENTES!$C:$C,VAREJO!$C51,CLIENTES!$M:$M) -> 0 | AJ51: =IF(G51>=100%,2,0) -> 2 | AK51: =IF(J51>=100%,2,0) -> 2 | AL51: =IF(M51>=100%,2,0) -> 0 | AM51: =IF(P51>=100%,2,0) -> 0 | AO51: =IF($V51>=100%,10,0) -> 0 | AQ51: =AA51 -> 15 | AR51: =$AE51 -> 14 | AT51: =Tabela3[[#This Row],[BARRACA MONTADA]]*5 -> 0 | AU51: =Tabela3[[#This Row],[PONTO EXTRA]]*5 -> 0 | AW51: =SUM(Tabela35[[#This Row],[POSI ABRIL]:[PONTO EXTRA]]) -> 33 | AX51: =_xlfn.RANK.EQ(Tabela35[[#This Row],[TOTAL]],Tabela35[TOTAL],0)& "º" -> 49º | AY51: =COUNTA(_xlfn.UNIQUE(_xlfn.VSTACK(AD51,Y51,S51,C51))) -> 1
C52: 3980 | D52: JLLE CONVEN PC | E52: 50 | F52: 57 | G52: 1.14 | H52: 58 | I52: 67 | J52: 1.1551724 | K52: 58 | L52: 25 | M52: 0.43103448 | N52: 0 | S52: 3980 | T52: 32499.52 | U52: 20866.75 | V52: 0.64206333 | Y52: 3980 | Z52: 24 | AA52: 38 | AD52: 3980 | AE52: 29 | AG52: =SUMIF(CLIENTES!$C:$C,VAREJO!$C52,CLIENTES!$L:$L) -> 0 | AH52: =SUMIF(CLIENTES!$C:$C,VAREJO!$C52,CLIENTES!$M:$M) -> 0 | AJ52: =IF(G52>=100%,2,0) -> 2 | AK52: =IF(J52>=100%,2,0) -> 2 | AL52: =IF(M52>=100%,2,0) -> 0 | AM52: =IF(P52>=100%,2,0) -> 0 | AO52: =IF($V52>=100%,10,0) -> 0 | AQ52: =AA52 -> 38 | AR52: =$AE52 -> 29 | AT52: =Tabela3[[#This Row],[BARRACA MONTADA]]*5 -> 0 | AU52: =Tabela3[[#This Row],[PONTO EXTRA]]*5 -> 0 | AW52: =SUM(Tabela35[[#This Row],[POSI ABRIL]:[PONTO EXTRA]]) -> 71 | AX52: =_xlfn.RANK.EQ(Tabela35[[#This Row],[TOTAL]],Tabela35[TOTAL],0)& "º" -> 30º | AY52: =COUNTA(_xlfn.UNIQUE(_xlfn.VSTACK(AD52,Y52,S52,C52))) -> 1
C53: 4037 | D53: JLLE-SUL M | E53: 58 | F53: 75 | G53: 1.2931034 | H53: 67 | I53: 68 | J53: 1.0149254 | K53: 67 | L53: 23 | M53: 0.34328358 | N53: 0 | S53: 4037 | T53: 12999.61 | U53: 17454.82 | V53: 1.3427187 | Y53: 4037 | Z53: 37 | AA53: 19 | AD53: 4037 | AE53: 15 | AG53: =SUMIF(CLIENTES!$C:$C,VAREJO!$C53,CLIENTES!$L:$L) -> 2 | AH53: =SUMIF(CLIENTES!$C:$C,VAREJO!$C53,CLIENTES!$M:$M) -> 0 | AJ53: =IF(G53>=100%,2,0) -> 2 | AK53: =IF(J53>=100%,2,0) -> 2 | AL53: =IF(M53>=100%,2,0) -> 0 | AM53: =IF(P53>=100%,2,0) -> 0 | AO53: =IF($V53>=100%,10,0) -> 10 | AQ53: =AA53 -> 19 | AR53: =$AE53 -> 15 | AT53: =Tabela3[[#This Row],[BARRACA MONTADA]]*5 -> 10 | AU53: =Tabela3[[#This Row],[PONTO EXTRA]]*5 -> 0 | AW53: =SUM(Tabela35[[#This Row],[POSI ABRIL]:[PONTO EXTRA]]) -> 58 | AX53: =_xlfn.RANK.EQ(Tabela35[[#This Row],[TOTAL]],Tabela35[TOTAL],0)& "º" -> 37º | AY53: =COUNTA(_xlfn.UNIQUE(_xlfn.VSTACK(AD53,Y53,S53,C53))) -> 1
C54: 4044 | D54: ITAPOA M | E54: 46 | F54: 62 | G54: 1.3478261 | H54: 54 | I54: 71 | J54: 1.3148148 | K54: 54 | L54: 36 | M54: 0.66666667 | N54: 0 | S54: 4044 | T54: 31500.55 | U54: 34022.61 | V54: 1.080064 | Y54: 4044 | Z54: 46 | AA54: 44 | AD54: 4044 | AE54: 38 | AG54: =SUMIF(CLIENTES!$C:$C,VAREJO!$C54,CLIENTES!$L:$L) -> 7 | AH54: =SUMIF(CLIENTES!$C:$C,VAREJO!$C54,CLIENTES!$M:$M) -> 0 | AJ54: =IF(G54>=100%,2,0) -> 2 | AK54: =IF(J54>=100%,2,0) -> 2 | AL54: =IF(M54>=100%,2,0) -> 0 | AM54: =IF(P54>=100%,2,0) -> 0 | AO54: =IF($V54>=100%,10,0) -> 10 | AQ54: =AA54 -> 44 | AR54: =$AE54 -> 38 | AT54: =Tabela3[[#This Row],[BARRACA MONTADA]]*5 -> 35 | AU54: =Tabela3[[#This Row],[PONTO EXTRA]]*5 -> 0 | AW54: =SUM(Tabela35[[#This Row],[POSI ABRIL]:[PONTO EXTRA]]) -> 131 | AX54: =_xlfn.RANK.EQ(Tabela35[[#This Row],[TOTAL]],Tabela35[TOTAL],0)& "º" -> 3º | AY54: =COUNTA(_xlfn.UNIQUE(_xlfn.VSTACK(AD54,Y54,S54,C54))) -> 1
C55: 4045 | D55: GUARAMIRIM M | E55: 97 | F55: 101 | G55: 1.0412371 | H55: 112 | I55: 118 | J55: 1.0535714 | K55: 112 | L55: 46 | M55: 0.41071429 | N55: 0 | S55: 4045 | T55: 38500.33 | U55: 52337.04 | V55: 1.359392 | Y55: 4045 | Z55: 9 | AA55: 30 | AD55: 4045 | AE55: 26 | AG55: =SUMIF(CLIENTES!$C:$C,VAREJO!$C55,CLIENTES!$L:$L) -> 1 | AH55: =SUMIF(CLIENTES!$C:$C,VAREJO!$C55,CLIENTES!$M:$M) -> 0 | AJ55: =IF(G55>=100%,2,0) -> 2 | AK55: =IF(J55>=100%,2,0) -> 2 | AL55: =IF(M55>=100%,2,0) -> 0 | AM55: =IF(P55>=100%,2,0) -> 0 | AO55: =IF($V55>=100%,10,0) -> 10 | AQ55: =AA55 -> 30 | AR55: =$AE55 -> 26 | AT55: =Tabela3[[#This Row],[BARRACA MONTADA]]*5 -> 5 | AU55: =Tabela3[[#This Row],[PONTO EXTRA]]*5 -> 0 | AW55: =SUM(Tabela35[[#This Row],[POSI ABRIL]:[PONTO EXTRA]]) -> 75 | AX55: =_xlfn.RANK.EQ(Tabela35[[#This Row],[TOTAL]],Tabela35[TOTAL],0)& "º" -> 28º | AY55: =COUNTA(_xlfn.UNIQUE(_xlfn.VSTACK(AD55,Y55,S55,C55))) -> 1
C56: 4083 | D56: SAO BENTO M | E56: 64 | F56: 48 | G56: 0.75 | H56: 74 | I56: 65 | J56: 0.87837838 | K56: 74 | L56: 30 | M56: 0.40540541 | N56: 0 | S56: 4083 | T56: 53000.39 | U56: 30835.34 | V56: 0.58179459 | Y56: 4083 | Z56: 8 | AA56: 17 | AD56: 4083 | AE56: 12 | AG56: =SUMIF(CLIENTES!$C:$C,VAREJO!$C56,CLIENTES!$L:$L) -> 4 | AH56: =SUMIF(CLIENTES!$C:$C,VAREJO!$C56,CLIENTES!$M:$M) -> 0 | AJ56: =IF(G56>=100%,2,0) -> 0 | AK56: =IF(J56>=100%,2,0) -> 0 | AL56: =IF(M56>=100%,2,0) -> 0 | AM56: =IF(P56>=100%,2,0) -> 0 | AO56: =IF($V56>=100%,10,0) -> 0 | AQ56: =AA56 -> 17 | AR56: =$AE56 -> 12 | AT56: =Tabela3[[#This Row],[BARRACA MONTADA]]*5 -> 20 | AU56: =Tabela3[[#This Row],[PONTO EXTRA]]*5 -> 0 | AW56: =SUM(Tabela35[[#This Row],[POSI ABRIL]:[PONTO EXTRA]]) -> 49 | AX56: =_xlfn.RANK.EQ(Tabela35[[#This Row],[TOTAL]],Tabela35[TOTAL],0)& "º" -> 41º | AY56: =COUNTA(_xlfn.UNIQUE(_xlfn.VSTACK(AD56,Y56,S56,C56))) -> 1
C57: 4084 | D57: MAFRA M | E57: 66 | F57: 53 | G57: 0.8030303 | H57: 76 | I57: 68 | J57: 0.89473684 | K57: 76 | L57: 37 | M57: 0.48684211 | N57: 0 | S57: 4084 | T57: 16500 | U57: 17948.36 | V57: 1.0877794 | Y57: 4084 | Z57: 39 | AA57: 13 | AD57: 4084 | AE57: 8 | AG57: =SUMIF(CLIENTES!$C:$C,VAREJO!$C57,CLIENTES!$L:$L) -> 4 | AH57: =SUMIF(CLIENTES!$C:$C,VAREJO!$C57,CLIENTES!$M:$M) -> 0 | AJ57: =IF(G57>=100%,2,0) -> 0 | AK57: =IF(J57>=100%,2,0) -> 0 | AL57: =IF(M57>=100%,2,0) -> 0 | AM57: =IF(P57>=100%,2,0) -> 0 | AO57: =IF($V57>=100%,10,0) -> 10 | AQ57: =AA57 -> 13 | AR57: =$AE57 -> 8 | AT57: =Tabela3[[#This Row],[BARRACA MONTADA]]*5 -> 20 | AU57: =Tabela3[[#This Row],[PONTO EXTRA]]*5 -> 0 | AW57: =SUM(Tabela35[[#This Row],[POSI ABRIL]:[PONTO EXTRA]]) -> 51 | AX57: =_xlfn.RANK.EQ(Tabela35[[#This Row],[TOTAL]],Tabela35[TOTAL],0)& "º" -> 40º | AY57: =COUNTA(_xlfn.UNIQUE(_xlfn.VSTACK(AD57,Y57,S57,C57))) -> 1
B58: SUL M | C58: 4005 | D58: TUBARAO M | E58: 74 | F58: 81 | G58: 1.0945946 | H58: 86 | I58: 82 | J58: 0.95348837 | K58: 86 | L58: 36 | M58: 0.41860465 | N58: 0 | R58: SUL M | S58: 4005 | T58: 18499.94 | U58: 17817.12 | V58: 0.96309069 | X58: SUL M | Y58: 4005 | Z58: 15 | AA58: 35 | AC58: SUL M | AD58: 4005 | AE58: 30 | AG58: =SUMIF(CLIENTES!$C:$C,VAREJO!$C58,CLIENTES!$L:$L) -> 2 | AH58: =SUMIF(CLIENTES!$C:$C,VAREJO!$C58,CLIENTES!$M:$M) -> 0 | AJ58: =IF(G58>=100%,2,0) -> 2 | AK58: =IF(J58>=100%,2,0) -> 0 | AL58: =IF(M58>=100%,2,0) -> 0 | AM58: =IF(P58>=100%,2,0) -> 0 | AO58: =IF($V58>=100%,10,0) -> 0 | AQ58: =AA58 -> 35 | AR58: =$AE58 -> 30 | AT58: =Tabela3[[#This Row],[BARRACA MONTADA]]*5 -> 10 | AU58: =Tabela3[[#This Row],[PONTO EXTRA]]*5 -> 0 | AW58: =SUM(Tabela35[[#This Row],[POSI ABRIL]:[PONTO EXTRA]]) -> 77 | AX58: =_xlfn.RANK.EQ(Tabela35[[#This Row],[TOTAL]],Tabela35[TOTAL],0)& "º" -> 25º | AY58: =COUNTA(_xlfn.UNIQUE(_xlfn.VSTACK(AD58,Y58,S58,C58))) -> 1
C59: 4009 | D59: ICARA M | E59: 73 | F59: 83 | G59: 1.1369863 | H59: 84 | I59: 96 | J59: 1.1428571 | K59: 85 | L59: 24 | M59: 0.28235294 | N59: 0 | S59: 4009 | T59: 10999.67 | U59: 9933.44 | V59: 0.90306709 | Y59: 4009 | Z59: 4 | AA59: 21 | AD59: 4009 | AE59: 18 | AG59: =SUMIF(CLIENTES!$C:$C,VAREJO!$C59,CLIENTES!$L:$L) -> 2 | AH59: =SUMIF(CLIENTES!$C:$C,VAREJO!$C59,CLIENTES!$M:$M) -> 0 | AJ59: =IF(G59>=100%,2,0) -> 2 | AK59: =IF(J59>=100%,2,0) -> 2 | AL59: =IF(M59>=100%,2,0) -> 0 | AM59: =IF(P59>=100%,2,0) -> 0 | AO59: =IF($V59>=100%,10,0) -> 0 | AQ59: =AA59 -> 21 | AR59: =$AE59 -> 18 | AT59: =Tabela3[[#This Row],[BARRACA MONTADA]]*5 -> 10 | AU59: =Tabela3[[#This Row],[PONTO EXTRA]]*5 -> 0 | AW59: =SUM(Tabela35[[#This Row],[POSI ABRIL]:[PONTO EXTRA]]) -> 53 | AX59: =_xlfn.RANK.EQ(Tabela35[[#This Row],[TOTAL]],Tabela35[TOTAL],0)& "º" -> 38º | AY59: =COUNTA(_xlfn.UNIQUE(_xlfn.VSTACK(AD59,Y59,S59,C59))) -> 1
C60: 4010 | D60: CRICIUMA CONV | E60: 74 | F60: 87 | G60: 1.1756757 | H60: 86 | I60: 92 | J60: 1.0697674 | K60: 86 | L60: 69 | M60: 0.80232558 | N60: 0 | S60: 4010 | T60: 30000.09 | U60: 23183.63 | V60: 0.77278535 | Y60: 4010 | Z60: 16 | AA60: 38 | AD60: 4010 | AE60: 33 | AG60: =SUMIF(CLIENTES!$C:$C,VAREJO!$C60,CLIENTES!$L:$L) -> 2 | AH60: =SUMIF(CLIENTES!$C:$C,VAREJO!$C60,CLIENTES!$M:$M) -> 0 | AJ60: =IF(G60>=100%,2,0) -> 2 | AK60: =IF(J60>=100%,2,0) -> 2 | AL60: =IF(M60>=100%,2,0) -> 0 | AM60: =IF(P60>=100%,2,0) -> 0 | AO60: =IF($V60>=100%,10,0) -> 0 | AQ60: =AA60 -> 38 | AR60: =$AE60 -> 33 | AT60: =Tabela3[[#This Row],[BARRACA MONTADA]]*5 -> 10 | AU60: =Tabela3[[#This Row],[PONTO EXTRA]]*5 -> 0 | AW60: =SUM(Tabela35[[#This Row],[POSI ABRIL]:[PONTO EXTRA]]) -> 85 | AX60: =_xlfn.RANK.EQ(Tabela35[[#This Row],[TOTAL]],Tabela35[TOTAL],0)& "º" -> 19º | AY60: =COUNTA(_xlfn.UNIQUE(_xlfn.VSTACK(AD60,Y60,S60,C60))) -> 1
C61: 4015 | D61: CRICIUMA M | E61: 71 | F61: 55 | G61: 0.77464789 | H61: 81 | I61: 84 | J61: 1.037037 | K61: 82 | L61: 42 | M61: 0.51219512 | N61: 0 | S61: 4015 | T61: 13999.58 | U61: 11495.03 | V61: 0.8210982 | Y61: 4015 | Z61: 52 | AA61: 31 | AD61: 4015 | AE61: 28 | AG61: =SUMIF(CLIENTES!$C:$C,VAREJO!$C61,CLIENTES!$L:$L) -> 1 | AH61: =SUMIF(CLIENTES!$C:$C,VAREJO!$C61,CLIENTES!$M:$M) -> 0 | AJ61: =IF(G61>=100%,2,0) -> 0 | AK61: =IF(J61>=100%,2,0) -> 2 | AL61: =IF(M61>=100%,2,0) -> 0 | AM61: =IF(P61>=100%,2,0) -> 0 | AO61: =IF($V61>=100%,10,0) -> 0 | AQ61: =AA61 -> 31 | AR61: =$AE61 -> 28 | AT61: =Tabela3[[#This Row],[BARRACA MONTADA]]*5 -> 5 | AU61: =Tabela3[[#This Row],[PONTO EXTRA]]*5 -> 0 | AW61: =SUM(Tabela35[[#This Row],[POSI ABRIL]:[PONTO EXTRA]]) -> 66 | AX61: =_xlfn.RANK.EQ(Tabela35[[#This Row],[TOTAL]],Tabela35[TOTAL],0)& "º" -> 32º | AY61: =COUNTA(_xlfn.UNIQUE(_xlfn.VSTACK(AD61,Y61,S61,C61))) -> 1
C62: 4016 | D62: BRACO NORTE M | E62: 88 | F62: 96 | G62: 1.0909091 | H62: 101 | I62: 100 | J62: 0.99009901 | K62: 102 | L62: 64 | M62: 0.62745098 | N62: 0 | S62: 4016 | T62: 33000 | U62: 25375.45 | V62: 0.76895303 | Y62: 4016 | Z62: 8 | AA62: 38 | AD62: 4016 | AE62: 36 | AG62: =SUMIF(CLIENTES!$C:$C,VAREJO!$C62,CLIENTES!$L:$L) -> 0 | AH62: =SUMIF(CLIENTES!$C:$C,VAREJO!$C62,CLIENTES!$M:$M) -> 0 | AJ62: =IF(G62>=100%,2,0) -> 2 | AK62: =IF(J62>=100%,2,0) -> 0 | AL62: =IF(M62>=100%,2,0) -> 0 | AM62: =IF(P62>=100%,2,0) -> 0 | AO62: =IF($V62>=100%,10,0) -> 0 | AQ62: =AA62 -> 38 | AR62: =$AE62 -> 36 | AT62: =Tabela3[[#This Row],[BARRACA MONTADA]]*5 -> 0 | AU62: =Tabela3[[#This Row],[PONTO EXTRA]]*5 -> 0 | AW62: =SUM(Tabela35[[#This Row],[POSI ABRIL]:[PONTO EXTRA]]) -> 76 | AX62: =_xlfn.RANK.EQ(Tabela35[[#This Row],[TOTAL]],Tabela35[TOTAL],0)& "º" -> 27º | AY62: =COUNTA(_xlfn.UNIQUE(_xlfn.VSTACK(AD62,Y62,S62,C62))) -> 1
C63: 4017 | D63: GAROPABA M | E63: 60 | F63: 80 | G63: 1.3333333 | H63: 70 | I63: 71 | J63: 1.0142857 | K63: 70 | L63: 42 | M63: 0.6 | N63: 0 | S63: 4017 | T63: 44999.64 | U63: 27497.08 | V63: 0.61105111 | Y63: 4017 | Z63: 19 | AA63: 46 | AD63: 4017 | AE63: 35 | AG63: =SUMIF(CLIENTES!$C:$C,VAREJO!$C63,CLIENTES!$L:$L) -> 3 | AH63: =SUMIF(CLIENTES!$C:$C,VAREJO!$C63,CLIENTES!$M:$M) -> 0 | AJ63: =IF(G63>=100%,2,0) -> 2 | AK63: =IF(J63>=100%,2,0) -> 2 | AL63: =IF(M63>=100%,2,0) -> 0 | AM63: =IF(P63>=100%,2,0) -> 0 | AO63: =IF($V63>=100%,10,0) -> 0 | AQ63: =AA63 -> 46 | AR63: =$AE63 -> 35 | AT63: =Tabela3[[#This Row],[BARRACA MONTADA]]*5 -> 15 | AU63: =Tabela3[[#This Row],[PONTO EXTRA]]*5 -> 0 | AW63: =SUM(Tabela35[[#This Row],[POSI ABRIL]:[PONTO EXTRA]]) -> 100 | AX63: =_xlfn.RANK.EQ(Tabela35[[#This Row],[TOTAL]],Tabela35[TOTAL],0)& "º" -> 13º | AY63: =COUNTA(_xlfn.UNIQUE(_xlfn.VSTACK(AD63,Y63,S63,C63))) -> 1
C64: 4018 | D64: SOMBRIO M | E64: 58 | F64: 68 | G64: 1.1724138 | H64: 67 | I64: 67 | J64: 1 | K64: 67 | L64: 33 | M64: 0.49253731 | N64: 0 | S64: 4018 | T64: 11999.64 | U64: 9418.41 | V64: 0.78489105 | Y64: 4018 | Z64: 13 | AA64: 15 | AD64: 4018 | AE64: 14 | AG64: =SUMIF(CLIENTES!$C:$C,VAREJO!$C64,CLIENTES!$L:$L) -> 0 | AH64: =SUMIF(CLIENTES!$C:$C,VAREJO!$C64,CLIENTES!$M:$M) -> 0 | AJ64: =IF(G64>=100%,2,0) -> 2 | AK64: =IF(J64>=100%,2,0) -> 2 | AL64: =IF(M64>=100%,2,0) -> 0 | AM64: =IF(P64>=100%,2,0) -> 0 | AO64: =IF($V64>=100%,10,0) -> 0 | AQ64: =AA64 -> 15 | AR64: =$AE64 -> 14 | AT64: =Tabela3[[#This Row],[BARRACA MONTADA]]*5 -> 0 | AU64: =Tabela3[[#This Row],[PONTO EXTRA]]*5 -> 0 | AW64: =SUM(Tabela35[[#This Row],[POSI ABRIL]:[PONTO EXTRA]]) -> 33 | AX64: =_xlfn.RANK.EQ(Tabela35[[#This Row],[TOTAL]],Tabela35[TOTAL],0)& "º" -> 49º | AY64: =COUNTA(_xlfn.UNIQUE(_xlfn.VSTACK(AD64,Y64,S64,C64))) -> 1
C65: 4079 | D65: JAGUARUNA M | E65: 80 | F65: 49 | G65: 0.6125 | H65: 93 | I65: 77 | J65: 0.82795699 | K65: 93 | L65: 26 | M65: 0.27956989 | N65: 0 | S65: 4079 | T65: 12500.12 | U65: 9726.59 | V65: 0.77811973 | Y65: 4079 | Z65: 12 | AA65: 21 | AD65: 4079 | AE65: 19 | AG65: =SUMIF(CLIENTES!$C:$C,VAREJO!$C65,CLIENTES!$L:$L) -> 0 | AH65: =SUMIF(CLIENTES!$C:$C,VAREJO!$C65,CLIENTES!$M:$M) -> 0 | AJ65: =IF(G65>=100%,2,0) -> 0 | AK65: =IF(J65>=100%,2,0) -> 0 | AL65: =IF(M65>=100%,2,0) -> 0 | AM65: =IF(P65>=100%,2,0) -> 0 | AO65: =IF($V65>=100%,10,0) -> 0 | AQ65: =AA65 -> 21 | AR65: =$AE65 -> 19 | AT65: =Tabela3[[#This Row],[BARRACA MONTADA]]*5 -> 0 | AU65: =Tabela3[[#This Row],[PONTO EXTRA]]*5 -> 0 | AW65: =SUM(Tabela35[[#This Row],[POSI ABRIL]:[PONTO EXTRA]]) -> 40 | AX65: =_xlfn.RANK.EQ(Tabela35[[#This Row],[TOTAL]],Tabela35[TOTAL],0)& "º" -> 44º | AY65: =COUNTA(_xlfn.UNIQUE(_xlfn.VSTACK(AD65,Y65,S65,C65))) -> 1
C66: 4080 | D66: ORLEANS M | E66: 75 | F66: 94 | G66: 1.2533333 | H66: 87 | I66: 95 | J66: 1.091954 | K66: 87 | L66: 81 | M66: 0.93103448 | N66: 0 | S66: 4080 | T66: 30000.09 | U66: 34676.91 | V66: 1.1558935 | Y66: 4080 | Z66: 58 | AA66: 36 | AD66: 4080 | AE66: 33 | AG66: =SUMIF(CLIENTES!$C:$C,VAREJO!$C66,CLIENTES!$L:$L) -> 8 | AH66: =SUMIF(CLIENTES!$C:$C,VAREJO!$C66,CLIENTES!$M:$M) -> 0 | AJ66: =IF(G66>=100%,2,0) -> 2 | AK66: =IF(J66>=100%,2,0) -> 2 | AL66: =IF(M66>=100%,2,0) -> 0 | AM66: =IF(P66>=100%,2,0) -> 0 | AO66: =IF($V66>=100%,10,0) -> 10 | AQ66: =AA66 -> 36 | AR66: =$AE66 -> 33 | AT66: =Tabela3[[#This Row],[BARRACA MONTADA]]*5 -> 40 | AU66: =Tabela3[[#This Row],[PONTO EXTRA]]*5 -> 0 | AW66: =SUM(Tabela35[[#This Row],[POSI ABRIL]:[PONTO EXTRA]]) -> 123 | AX66: =_xlfn.RANK.EQ(Tabela35[[#This Row],[TOTAL]],Tabela35[TOTAL],0)& "º" -> 7º | AY66: =COUNTA(_xlfn.UNIQUE(_xlfn.VSTACK(AD66,Y66,S66,C66))) -> 1
C67: 4081 | D67: ARARANGUA M | E67: 58 | F67: 66 | G67: 1.137931 | H67: 67 | I67: 70 | J67: 1.0447761 | K67: 67 | L67: 26 | M67: 0.3880597 | N67: 0 | S67: 4081 | T67: 10000.7 | U67: 6956.19 | V67: 0.69557031 | Y67: 4081 | Z67: 8 | AA67: 10 | AD67: 4081 | AE67: 10 | AG67: =SUMIF(CLIENTES!$C:$C,VAREJO!$C67,CLIENTES!$L:$L) -> 0 | AH67: =SUMIF(CLIENTES!$C:$C,VAREJO!$C67,CLIENTES!$M:$M) -> 0 | AJ67: =IF(G67>=100%,2,0) -> 2 | AK67: =IF(J67>=100%,2,0) -> 2 | AL67: =IF(M67>=100%,2,0) -> 0 | AM67: =IF(P67>=100%,2,0) -> 0 | AO67: =IF($V67>=100%,10,0) -> 0 | AQ67: =AA67 -> 10 | AR67: =$AE67 -> 10 | AT67: =Tabela3[[#This Row],[BARRACA MONTADA]]*5 -> 0 | AU67: =Tabela3[[#This Row],[PONTO EXTRA]]*5 -> 0 | AW67: =SUM(Tabela35[[#This Row],[POSI ABRIL]:[PONTO EXTRA]]) -> 24 | AX67: =_xlfn.RANK.EQ(Tabela35[[#This Row],[TOTAL]],Tabela35[TOTAL],0)& "º" -> 51º | AY67: =COUNTA(_xlfn.UNIQUE(_xlfn.VSTACK(AD67,Y67,S67,C67))) -> 1
C68: 4082 | D68: TUBARAO CONV | E68: 57 | F68: 68 | G68: 1.1929825 | H68: 65 | I68: 85 | J68: 1.3076923 | K68: 66 | L68: 66 | M68: 1 | N68: 0 | S68: 4082 | T68: 18499.94 | U68: 9470.94 | V68: 0.51194436 | Y68: 4082 | Z68: 1 | AA68: 24 | AD68: 4082 | AE68: 17 | AG68: =SUMIF(CLIENTES!$C:$C,VAREJO!$C68,CLIENTES!$L:$L) -> 0 | AH68: =SUMIF(CLIENTES!$C:$C,VAREJO!$C68,CLIENTES!$M:$M) -> 0 | AJ68: =IF(G68>=100%,2,0) -> 2 | AK68: =IF(J68>=100%,2,0) -> 2 | AL68: =IF(M68>=100%,2,0) -> 2 | AM68: =IF(P68>=100%,2,0) -> 0 | AO68: =IF($V68>=100%,10,0) -> 0 | AQ68: =AA68 -> 24 | AR68: =$AE68 -> 17 | AT68: =Tabela3[[#This Row],[BARRACA MONTADA]]*5 -> 0 | AU68: =Tabela3[[#This Row],[PONTO EXTRA]]*5 -> 0 | AW68: =SUM(Tabela35[[#This Row],[POSI ABRIL]:[PONTO EXTRA]]) -> 47 | AX68: =_xlfn.RANK.EQ(Tabela35[[#This Row],[TOTAL]],Tabela35[TOTAL],0)& "º" -> 42º | AY68: =COUNTA(_xlfn.UNIQUE(_xlfn.VSTACK(AD68,Y68,S68,C68))) -> 1
B69: VALE M | C69: 3912 | D69: POMERODE M | E69: 68 | F69: 48 | G69: 0.70588235 | H69: 78 | I69: 45 | J69: 0.57692308 | K69: 79 | L69: 29 | M69: 0.36708861 | N69: 0 | R69: VALE M | S69: 3912 | T69: 13999.58 | U69: 8685.22 | V69: 0.62039147 | X69: VALE M | Y69: 3912 | Z69: 20 | AA69: 7 | AC69: VALE M | AD69: 3912 | AE69: 7 | AG69: =SUMIF(CLIENTES!$C:$C,VAREJO!$C69,CLIENTES!$L:$L) -> 0 | AH69: =SUMIF(CLIENTES!$C:$C,VAREJO!$C69,CLIENTES!$M:$M) -> 0 | AJ69: =IF(G69>=100%,2,0) -> 0 | AK69: =IF(J69>=100%,2,0) -> 0 | AL69: =IF(M69>=100%,2,0) -> 0 | AM69: =IF(P69>=100%,2,0) -> 0 | AO69: =IF($V69>=100%,10,0) -> 0 | AQ69: =AA69 -> 7 | AR69: =$AE69 -> 7 | AT69: =Tabela3[[#This Row],[BARRACA MONTADA]]*5 -> 0 | AU69: =Tabela3[[#This Row],[PONTO EXTRA]]*5 -> 0 | AW69: =SUM(Tabela35[[#This Row],[POSI ABRIL]:[PONTO EXTRA]]) -> 14 | AX69: =_xlfn.RANK.EQ(Tabela35[[#This Row],[TOTAL]],Tabela35[TOTAL],0)& "º" -> 53º | AY69: =COUNTA(_xlfn.UNIQUE(_xlfn.VSTACK(AD69,Y69,S69,C69))) -> 1
C70: 3933 | D70: BNU CONV SUL | E70: 74 | F70: 84 | G70: 1.1351351 | H70: 86 | I70: 84 | J70: 0.97674419 | K70: 86 | L70: 63 | M70: 0.73255814 | N70: 0 | S70: 3933 | T70: 13500.09 | U70: 12247.22 | V70: 0.90719543 | Y70: 3933 | Z70: 38 | AA70: 47 | AD70: 3933 | AE70: 44 | AG70: =SUMIF(CLIENTES!$C:$C,VAREJO!$C70,CLIENTES!$L:$L) -> 0 | AH70: =SUMIF(CLIENTES!$C:$C,VAREJO!$C70,CLIENTES!$M:$M) -> 0 | AJ70: =IF(G70>=100%,2,0) -> 2 | AK70: =IF(J70>=100%,2,0) -> 0 | AL70: =IF(M70>=100%,2,0) -> 0 | AM70: =IF(P70>=100%,2,0) -> 0 | AO70: =IF($V70>=100%,10,0) -> 0 | AQ70: =AA70 -> 47 | AR70: =$AE70 -> 44 | AT70: =Tabela3[[#This Row],[BARRACA MONTADA]]*5 -> 0 | AU70: =Tabela3[[#This Row],[PONTO EXTRA]]*5 -> 0 | AW70: =SUM(Tabela35[[#This Row],[POSI ABRIL]:[PONTO EXTRA]]) -> 93 | AX70: =_xlfn.RANK.EQ(Tabela35[[#This Row],[TOTAL]],Tabela35[TOTAL],0)& "º" -> 14º | AY70: =COUNTA(_xlfn.UNIQUE(_xlfn.VSTACK(AD70,Y70,S70,C70))) -> 1
C71: 4058 | D71: BNU CONV NORTE | E71: 72 | F71: 84 | G71: 1.1666667 | H71: 83 | I71: 86 | J71: 1.0361446 | K71: 84 | L71: 73 | M71: 0.86904762 | N71: 0 | S71: 4058 | T71: 17999.45 | U71: 20022.54 | V71: 1.1123973 | Y71: 4058 | Z71: 16 | AA71: 35 | AD71: 4058 | AE71: 29 | AG71: =SUMIF(CLIENTES!$C:$C,VAREJO!$C71,CLIENTES!$L:$L) -> 1 | AH71: =SUMIF(CLIENTES!$C:$C,VAREJO!$C71,CLIENTES!$M:$M) -> 0 | AJ71: =IF(G71>=100%,2,0) -> 2 | AK71: =IF(J71>=100%,2,0) -> 2 | AL71: =IF(M71>=100%,2,0) -> 0 | AM71: =IF(P71>=100%,2,0) -> 0 | AO71: =IF($V71>=100%,10,0) -> 10 | AQ71: =AA71 -> 35 | AR71: =$AE71 -> 29 | AT71: =Tabela3[[#This Row],[BARRACA MONTADA]]*5 -> 5 | AU71: =Tabela3[[#This Row],[PONTO EXTRA]]*5 -> 0 | AW71: =SUM(Tabela35[[#This Row],[POSI ABRIL]:[PONTO EXTRA]]) -> 83 | AX71: =_xlfn.RANK.EQ(Tabela35[[#This Row],[TOTAL]],Tabela35[TOTAL],0)& "º" -> 23º | AY71: =COUNTA(_xlfn.UNIQUE(_xlfn.VSTACK(AD71,Y71,S71,C71))) -> 1
C72: 4059 | D72: BNU-FOR M | E72: 63 | F72: 45 | G72: 0.71428571 | H72: 73 | I72: 45 | J72: 0.61643836 | K72: 73 | L72: 35 | M72: 0.47945205 | N72: 0 | S72: 4059 | T72: 19499.91 | U72: 10022.93 | V72: 0.51399878 | Y72: 4059 | Z72: 19 | AA72: 21 | AD72: 4059 | AE72: 16 | AG72: =SUMIF(CLIENTES!$C:$C,VAREJO!$C72,CLIENTES!$L:$L) -> 0 | AH72: =SUMIF(CLIENTES!$C:$C,VAREJO!$C72,CLIENTES!$M:$M) -> 0 | AJ72: =IF(G72>=100%,2,0) -> 0 | AK72: =IF(J72>=100%,2,0) -> 0 | AL72: =IF(M72>=100%,2,0) -> 0 | AM72: =IF(P72>=100%,2,0) -> 0 | AO72: =IF($V72>=100%,10,0) -> 0 | AQ72: =AA72 -> 21 | AR72: =$AE72 -> 16 | AT72: =Tabela3[[#This Row],[BARRACA MONTADA]]*5 -> 0 | AU72: =Tabela3[[#This Row],[PONTO EXTRA]]*5 -> 0 | AW72: =SUM(Tabela35[[#This Row],[POSI ABRIL]:[PONTO EXTRA]]) -> 37 | AX72: =_xlfn.RANK.EQ(Tabela35[[#This Row],[TOTAL]],Tabela35[TOTAL],0)& "º" -> 46º | AY72: =COUNTA(_xlfn.UNIQUE(_xlfn.VSTACK(AD72,Y72,S72,C72))) -> 1
C73: 4060 | D73: GASPAR M | E73: 64 | F73: 42 | G73: 0.65625 | H73: 74 | I73: 81 | J73: 1.0945946 | K73: 74 | L73: 67 | M73: 0.90540541 | N73: 0 | S73: 4060 | T73: 28000.15 | U73: 17779.94 | V73: 0.63499446 | Y73: 4060 | Z73: 32 | AA73: 28 | AD73: 4060 | AE73: 26 | AG73: =SUMIF(CLIENTES!$C:$C,VAREJO!$C73,CLIENTES!$L:$L) -> 1 | AH73: =SUMIF(CLIENTES!$C:$C,VAREJO!$C73,CLIENTES!$M:$M) -> 0 | AJ73: =IF(G73>=100%,2,0) -> 0 | AK73: =IF(J73>=100%,2,0) -> 2 | AL73: =IF(M73>=100%,2,0) -> 0 | AM73: =IF(P73>=100%,2,0) -> 0 | AO73: =IF($V73>=100%,10,0) -> 0 | AQ73: =AA73 -> 28 | AR73: =$AE73 -> 26 | AT73: =Tabela3[[#This Row],[BARRACA MONTADA]]*5 -> 5 | AU73: =Tabela3[[#This Row],[PONTO EXTRA]]*5 -> 0 | AW73: =SUM(Tabela35[[#This Row],[POSI ABRIL]:[PONTO EXTRA]]) -> 61 | AX73: =_xlfn.RANK.EQ(Tabela35[[#This Row],[TOTAL]],Tabela35[TOTAL],0)& "º" -> 34º | AY73: =COUNTA(_xlfn.UNIQUE(_xlfn.VSTACK(AD73,Y73,S73,C73))) -> 1
C74: 4062 | D74: INDAIAL M | E74: 76 | F74: 86 | G74: 1.1315789 | H74: 89 | I74: 88 | J74: 0.98876404 | K74: 89 | L74: 57 | M74: 0.64044944 | N74: 0 | S74: 4062 | T74: 27499.67 | U74: 19784.4 | V74: 0.71944136 | Y74: 4062 | Z74: 19 | AA74: 18 | AD74: 4062 | AE74: 16 | AG74: =SUMIF(CLIENTES!$C:$C,VAREJO!$C74,CLIENTES!$L:$L) -> 0 | AH74: =SUMIF(CLIENTES!$C:$C,VAREJO!$C74,CLIENTES!$M:$M) -> 0 | AJ74: =IF(G74>=100%,2,0) -> 2 | AK74: =IF(J74>=100%,2,0) -> 0 | AL74: =IF(M74>=100%,2,0) -> 0 | AM74: =IF(P74>=100%,2,0) -> 0 | AO74: =IF($V74>=100%,10,0) -> 0 | AQ74: =AA74 -> 18 | AR74: =$AE74 -> 16 | AT74: =Tabela3[[#This Row],[BARRACA MONTADA]]*5 -> 0 | AU74: =Tabela3[[#This Row],[PONTO EXTRA]]*5 -> 0 | AW74: =SUM(Tabela35[[#This Row],[POSI ABRIL]:[PONTO EXTRA]]) -> 36 | AX74: =_xlfn.RANK.EQ(Tabela35[[#This Row],[TOTAL]],Tabela35[TOTAL],0)& "º" -> 47º | AY74: =COUNTA(_xlfn.UNIQUE(_xlfn.VSTACK(AD74,Y74,S74,C74))) -> 1
C75: 4069 | D75: RIO SUL M | E75: 69 | F75: 70 | G75: 1.0144928 | H75: 79 | I75: 57 | J75: 0.72151899 | K75: 80 | L75: 44 | M75: 0.55 | N75: 0 | S75: 4069 | T75: 32499.52 | U75: 24820.07 | V75: 0.76370574 | Y75: 4069 | Z75: 12 | AA75: 20 | AD75: 4069 | AE75: 17 | AG75: =SUMIF(CLIENTES!$C:$C,VAREJO!$C75,CLIENTES!$L:$L) -> 0 | AH75: =SUMIF(CLIENTES!$C:$C,VAREJO!$C75,CLIENTES!$M:$M) -> 0 | AJ75: =IF(G75>=100%,2,0) -> 2 | AK75: =IF(J75>=100%,2,0) -> 0 | AL75: =IF(M75>=100%,2,0) -> 0 | AM75: =IF(P75>=100%,2,0) -> 0 | AO75: =IF($V75>=100%,10,0) -> 0 | AQ75: =AA75 -> 20 | AR75: =$AE75 -> 17 | AT75: =Tabela3[[#This Row],[BARRACA MONTADA]]*5 -> 0 | AU75: =Tabela3[[#This Row],[PONTO EXTRA]]*5 -> 0 | AW75: =SUM(Tabela35[[#This Row],[POSI ABRIL]:[PONTO EXTRA]]) -> 39 | AX75: =_xlfn.RANK.EQ(Tabela35[[#This Row],[TOTAL]],Tabela35[TOTAL],0)& "º" -> 45º | AY75: =COUNTA(_xlfn.UNIQUE(_xlfn.VSTACK(AD75,Y75,S75,C75))) -> 1
C76: 4070 | D76: IBIRAMA M | E76: 80 | F76: 51 | G76: 0.6375 | H76: 93 | I76: 61 | J76: 0.65591398 | K76: 93 | L76: 44 | M76: 0.47311828 | N76: 0 | S76: 4070 | T76: 61499.64 | U76: 70075.04 | V76: 1.1394382 | Y76: 4070 | Z76: 10 | AA76: 19 | AD76: 4070 | AE76: 17 | AG76: =SUMIF(CLIENTES!$C:$C,VAREJO!$C76,CLIENTES!$L:$L) -> 0 | AH76: =SUMIF(CLIENTES!$C:$C,VAREJO!$C76,CLIENTES!$M:$M) -> 0 | AJ76: =IF(G76>=100%,2,0) -> 0 | AK76: =IF(J76>=100%,2,0) -> 0 | AL76: =IF(M76>=100%,2,0) -> 0 | AM76: =IF(P76>=100%,2,0) -> 0 | AO76: =IF($V76>=100%,10,0) -> 10 | AQ76: =AA76 -> 19 | AR76: =$AE76 -> 17 | AT76: =Tabela3[[#This Row],[BARRACA MONTADA]]*5 -> 0 | AU76: =Tabela3[[#This Row],[PONTO EXTRA]]*5 -> 0 | AW76: =SUM(Tabela35[[#This Row],[POSI ABRIL]:[PONTO EXTRA]]) -> 46 | AX76: =_xlfn.RANK.EQ(Tabela35[[#This Row],[TOTAL]],Tabela35[TOTAL],0)& "º" -> 43º | AY76: =COUNTA(_xlfn.UNIQUE(_xlfn.VSTACK(AD76,Y76,S76,C76))) -> 1
C77: 4087 | D77: TAIO M | E77: 57 | F77: 38 | G77: 0.66666667 | H77: 65 | I77: 36 | J77: 0.55384615 | K77: 66 | L77: 22 | M77: 0.33333333 | N77: 0 | S77: 4087 | T77: 22499.82 | U77: 17114.71 | V77: 0.76065986 | Y77: 4087 | Z77: 12 | AA77: 14 | AD77: 4087 | AE77: 10 | AG77: =SUMIF(CLIENTES!$C:$C,VAREJO!$C77,CLIENTES!$L:$L) -> 0 | AH77: =SUMIF(CLIENTES!$C:$C,VAREJO!$C77,CLIENTES!$M:$M) -> 0 | AJ77: =IF(G77>=100%,2,0) -> 0 | AK77: =IF(J77>=100%,2,0) -> 0 | AL77: =IF(M77>=100%,2,0) -> 0 | AM77: =IF(P77>=100%,2,0) -> 0 | AO77: =IF($V77>=100%,10,0) -> 0 | AQ77: =AA77 -> 14 | AR77: =$AE77 -> 10 | AT77: =Tabela3[[#This Row],[BARRACA MONTADA]]*5 -> 0 | AU77: =Tabela3[[#This Row],[PONTO EXTRA]]*5 -> 0 | AW77: =SUM(Tabela35[[#This Row],[POSI ABRIL]:[PONTO EXTRA]]) -> 24 | AX77: =_xlfn.RANK.EQ(Tabela35[[#This Row],[TOTAL]],Tabela35[TOTAL],0)& "º" -> 51º | AY77: =COUNTA(_xlfn.UNIQUE(_xlfn.VSTACK(AD77,Y77,S77,C77))) -> 1
C78: 4097 | D78: ITUPORANGA M | E78: 62 | F78: 86 | G78: 1.3870968 | H78: 72 | I78: 85 | J78: 1.1805556 | K78: 72 | L78: 77 | M78: 1.0694444 | N78: 0 | S78: 4097 | T78: 69999.88 | U78: 73487.73 | V78: 1.0498265 | Y78: 4097 | Z78: 33 | AA78: 27 | AD78: 4097 | AE78: 24 | AG78: =SUMIF(CLIENTES!$C:$C,VAREJO!$C78,CLIENTES!$L:$L) -> 11 | AH78: =SUMIF(CLIENTES!$C:$C,VAREJO!$C78,CLIENTES!$M:$M) -> 0 | AJ78: =IF(G78>=100%,2,0) -> 2 | AK78: =IF(J78>=100%,2,0) -> 2 | AL78: =IF(M78>=100%,2,0) -> 2 | AM78: =IF(P78>=100%,2,0) -> 0 | AO78: =IF($V78>=100%,10,0) -> 10 | AQ78: =AA78 -> 27 | AR78: =$AE78 -> 24 | AT78: =Tabela3[[#This Row],[BARRACA MONTADA]]*5 -> 55 | AU78: =Tabela3[[#This Row],[PONTO EXTRA]]*5 -> 0 | AW78: =SUM(Tabela35[[#This Row],[POSI ABRIL]:[PONTO EXTRA]]) -> 122 | AX78: =_xlfn.RANK.EQ(Tabela35[[#This Row],[TOTAL]],Tabela35[TOTAL],0)& "º" -> 8º | AY78: =COUNTA(_xlfn.UNIQUE(_xlfn.VSTACK(AD78,Y78,S78,C78))) -> 1
B81: VAREJO PC
B82: GRUPO | C82: VAREJO PC
B83: ST | C83: (Vários itens) | R83: GRUPO | S83: VAREJO PC | X83: GRUPO | Y83: VAREJO PC | AC83: GRUPO | AD83: VAREJO PC
X84: ST | Y84: (Vários itens) | AC84: ST | AD84: (Vários itens)
E85: MÊS | F85: Valores | T85: MÊS | U85: Valores
E86: ABRIL | H86: MAIO | K86: JUNHO | N86: JULHO | T86: TOTAL | X86: CONTAGEM ITENS | Z86: ITENS_GRUPO | AC86: POSITIVAÇÃO PAÇOQUITA | AG86: MERCHANDISING | AJ86: PONTUAÇÕES POSITIVAÇÃO | AO86: FATURAMENTO | AQ86: ITENS ESPECIAIS | AT86: MERCHANDISING | AW86: RANKING
B87: EQUIPE | C87: ID | D87: ÁREA | E87: META | F87: POSITIVAÇÃO | G87: % P | H87: META | I87: POSITIVAÇÃO | J87: % P | K87: META | L87: POSITIVAÇÃO | M87: % P | N87: META | O87: POSITIVAÇÃO | P87: % P | R87: EQUIPE | S87: ID | T87: META R$ | U87: R$ | V87: % R | X87: EQUIPE | Y87: ID | Z87: LANÇAMENTOS | AA87: PAÇOQUITA ZERO | AE87: PAÇOQUITA ZERO | AG87: BARRACA MONTADA | AH87: PONTO EXTRA | AJ87: POSI ABRIL | AK87: POSI MAIO | AL87: POSI JUNHO | AM87: POSI JULHO | AN87: Coluna1 | AO87: R$ TOTAL | AP87: Coluna12 | AQ87: LANÇAMENTOS | AR87: PAÇOCA ZERO | AS87: Coluna122 | AT87: BARRACAS | AU87: PONTO EXTRA | AV87: Coluna1222 | AW87: TOTAL | AX87: RANKING | AY87: VALIDAÇÃO VENDEDOR
B88: NORTE D | C88: 3818 | D88: CAN PC | E88: 42 | F88: 20 | G88: 0.47619048 | H88: 48 | I88: 36 | J88: 0.75 | K88: 48 | L88: 28 | M88: 0.58333333 | N88: 0 | R88: NORTE D | S88: 3818 | T88: 8499.24 | U88: 10609.77 | V88: 1.2483198 | X88: NORTE D | Y88: 3818 | Z88: 26 | AA88: 18 | AC88: NORTE D | AD88: 3818 | AE88: 10 | AJ88: =IF(G88>=100%,2,0) -> 0 | AK88: =IF(J88>=100%,2,0) -> 0 | AL88: =IF(M88>=100%,2,0) -> 0 | AM88: =IF(P88>=100%,2,0) -> 0 | AO88: =IF($V88>=100%,10,0) -> 10 | AQ88: =AA88 -> 18 | AR88: =$AE88 -> 10 | AT88: =Tabela37[[#This Row],[BARRACA MONTADA]] *3 -> 0 | AU88: =Tabela37[[#This Row],[PONTO EXTRA]] * 3 -> 0 | AW88: =SUM(Tabela358[[#This Row],[POSI ABRIL]:[PONTO EXTRA]]) -> 38 | AX88: =_xlfn.RANK.EQ(Tabela358[[#This Row],[TOTAL]],Tabela358[TOTAL],0)& "º" -> 3º | AY88: =COUNTA(_xlfn.UNIQUE(_xlfn.VSTACK(AD88,Y88,S88,C88))) -> 1
B89: SUL D | C89: 3681 | D89: LAGES-2 PC | E89: 73 | F89: 46 | G89: 0.63013699 | H89: 84 | I89: 45 | J89: 0.53571429 | K89: 85 | L89: 40 | M89: 0.47058824 | N89: 0 | R89: SUL D | S89: 3681 | T89: 31000.06 | U89: 17492.87 | V89: 0.56428504 | X89: SUL D | Y89: 3681 | Z89: 11 | AA89: 14 | AC89: SUL D | AD89: 3681 | AE89: 12 | AJ89: =IF(G89>=100%,2,0) -> 0 | AK89: =IF(J89>=100%,2,0) -> 0 | AL89: =IF(M89>=100%,2,0) -> 0 | AM89: =IF(P89>=100%,2,0) -> 0 | AO89: =IF($V89>=100%,10,0) -> 0 | AQ89: =AA89 -> 14 | AR89: =$AE89 -> 12 | AT89: =Tabela37[[#This Row],[BARRACA MONTADA]] *3 -> 0 | AU89: =Tabela37[[#This Row],[PONTO EXTRA]] * 3 -> 0 | AW89: =SUM(Tabela358[[#This Row],[POSI ABRIL]:[PONTO EXTRA]]) -> 26 | AX89: =_xlfn.RANK.EQ(Tabela358[[#This Row],[TOTAL]],Tabela358[TOTAL],0)& "º" -> 6º | AY89: =COUNTA(_xlfn.UNIQUE(_xlfn.VSTACK(AD89,Y89,S89,C89))) -> 1
C90: 3791 | D90: LAGES-1 PC | E90: 79 | F90: 66 | G90: 0.83544304 | H90: 91 | I90: 70 | J90: 0.76923077 | K90: 92 | L90: 56 | M90: 0.60869565 | N90: 0 | S90: 3791 | T90: 27499.67 | U90: 17237.25 | V90: 0.62681661 | Y90: 3791 | Z90: 38 | AA90: 15 | AD90: 3791 | AE90: 13 | AJ90: =IF(G90>=100%,2,0) -> 0 | AK90: =IF(J90>=100%,2,0) -> 0 | AL90: =IF(M90>=100%,2,0) -> 0 | AM90: =IF(P90>=100%,2,0) -> 0 | AO90: =IF($V90>=100%,10,0) -> 0 | AQ90: =AA90 -> 15 | AR90: =$AE90 -> 13 | AT90: =Tabela37[[#This Row],[BARRACA MONTADA]] *3 -> 0 | AU90: =Tabela37[[#This Row],[PONTO EXTRA]] * 3 -> 0 | AW90: =SUM(Tabela358[[#This Row],[POSI ABRIL]:[PONTO EXTRA]]) -> 28 | AX90: =_xlfn.RANK.EQ(Tabela358[[#This Row],[TOTAL]],Tabela358[TOTAL],0)& "º" -> 5º | AY90: =COUNTA(_xlfn.UNIQUE(_xlfn.VSTACK(AD90,Y90,S90,C90))) -> 1
B91: VENDAS INTERNAS | C91: 3272 | D91: VENDAS-2 | E91: 26 | F91: 46 | G91: 1.7692308 | H91: 30 | I91: 47 | J91: 1.5666667 | K91: 31 | L91: 38 | M91: 1.2258065 | N91: 0 | R91: VENDAS INTERNAS | S91: 3272 | T91: 32499.52 | U91: 14104.56 | V91: 0.43399287 | X91: VENDAS INTERNAS | Y91: 3272 | Z91: 11 | AA91: 26 | AC91: VENDAS INTERNAS | AD91: 3272 | AE91: 19 | AJ91: =IF(G91>=100%,2,0) -> 2 | AK91: =IF(J91>=100%,2,0) -> 2 | AL91: =IF(M91>=100%,2,0) -> 2 | AM91: =IF(P91>=100%,2,0) -> 0 | AO91: =IF($V91>=100%,10,0) -> 0 | AQ91: =AA91 -> 26 | AR91: =$AE91 -> 19 | AT91: =Tabela37[[#This Row],[BARRACA MONTADA]] *3 -> 0 | AU91: =Tabela37[[#This Row],[PONTO EXTRA]] * 3 -> 0 | AW91: =SUM(Tabela358[[#This Row],[POSI ABRIL]:[PONTO EXTRA]]) -> 51 | AX91: =_xlfn.RANK.EQ(Tabela358[[#This Row],[TOTAL]],Tabela358[TOTAL],0)& "º" -> 2º | AY91: =COUNTA(_xlfn.UNIQUE(_xlfn.VSTACK(AD91,Y91,S91,C91))) -> 1
C92: 3653 | D92: VENDAS-6 | E92: 19 | F92: 53 | G92: 2.7894737 | H92: 22 | I92: 64 | J92: 2.9090909 | K92: 23 | L92: 56 | M92: 2.4347826 | N92: 0 | S92: 3653 | T92: 27000.18 | U92: 21985.48 | V92: 0.81427161 | Y92: 3653 | Z92: 23 | AA92: 40 | AD92: 3653 | AE92: 33 | AJ92: =IF(G92>=100%,2,0) -> 2 | AK92: =IF(J92>=100%,2,0) -> 2 | AL92: =IF(M92>=100%,2,0) -> 2 | AM92: =IF(P92>=100%,2,0) -> 0 | AO92: =IF($V92>=100%,10,0) -> 0 | AQ92: =AA92 -> 40 | AR92: =$AE92 -> 33 | AT92: =Tabela37[[#This Row],[BARRACA MONTADA]] *3 -> 0 | AU92: =Tabela37[[#This Row],[PONTO EXTRA]] * 3 -> 0 | AW92: =SUM(Tabela358[[#This Row],[POSI ABRIL]:[PONTO EXTRA]]) -> 79 | AX92: =_xlfn.RANK.EQ(Tabela358[[#This Row],[TOTAL]],Tabela358[TOTAL],0)& "º" -> 1º | AY92: =COUNTA(_xlfn.UNIQUE(_xlfn.VSTACK(AD92,Y92,S92,C92))) -> 1
C93: 3670 | E93: 22 | F93: 43 | G93: 1.9545455 | H93: 25 | I93: 45 | J93: 1.8 | K93: 25 | L93: 42 | M93: 1.68 | N93: 0 | S93: 3670 | T93: 27000.18 | U93: 14703.52 | V93: 0.54457118 | Y93: 3670 | Z93: 15 | AA93: 14 | AD93: 3670 | AE93: 14 | AJ93: =IF(G93>=100%,2,0) -> 2 | AK93: =IF(J93>=100%,2,0) -> 2 | AL93: =IF(M93>=100%,2,0) -> 2 | AM93: =IF(P93>=100%,2,0) -> 0 | AO93: =IF($V93>=100%,10,0) -> 0 | AQ93: =AA93 -> 14 | AR93: =$AE93 -> 14 | AT93: =Tabela37[[#This Row],[BARRACA MONTADA]] *3 -> 0 | AU93: =Tabela37[[#This Row],[PONTO EXTRA]] * 3 -> 0 | AW93: =SUM(Tabela358[[#This Row],[POSI ABRIL]:[PONTO EXTRA]]) -> 34 | AX93: =_xlfn.RANK.EQ(Tabela358[[#This Row],[TOTAL]],Tabela358[TOTAL],0)& "º" -> 4º | AY93: =COUNTA(_xlfn.UNIQUE(_xlfn.VSTACK(AD93,Y93,S93,C93))) -> 1

Sheet MÉDIAS CONTAS
E4: MÊS | F4: Valores
E5: ABRIL | H5: MAIO | K5: JUNHO | N5: JULHO | Q5: Total META | R5: Total R$ | S5: Total % R
D6: EQUIPE | E6: META | F6: R$ | G6: % R | H6: META | I6: R$ | J6: % R | K6: META | L6: R$ | M6: % R | N6: META | O6: R$ | P6: % R
D7: FLP-SUL MC/KA D | E7: 480606.06 | F7: 421850.35 | G7: 0.87774663 | H7: 1330910 | I7: 1064643 | J7: 0.79993614 | K7: 628485 | L7: 748157.77 | M7: 1.1904147 | N7: 0 | Q7: 2440001.1 | R7: 2234651.1 | S7: 0.91584023
D8: FLP-SUL MC/KA M | E8: 102522.73 | F8: 139869.44 | G8: 1.3642774 | H8: 283909 | I8: 382496.17 | J8: 1.3472492 | K8: 134069 | L8: 89410.83 | M8: 0.6669016 | N8: 0 | Q8: 520500.73 | R8: 611776.44 | S8: 1.1753613
D9: NORTE MC/KA D | E9: 68053.03 | F9: 127159.6 | G9: 1.8685369 | H9: 188456 | I9: 186454.44 | J9: 0.98937917 | K9: 88991 | L9: 45351.23 | M9: 0.50961592 | N9: 0 | Q9: 345500.03 | R9: 358965.27 | S9: 1.0389732
D10: NORTE MC/KA M | E10: 248378.78 | F10: 183649.26 | G10: 0.73939191 | H10: 687819 | I10: 681417.28 | J10: 0.99069273 | K10: 324803 | L10: 153562.58 | M10: 0.47278683 | N10: 0 | Q10: 1261000.8 | R10: 1018629.1 | S10: 0.8077942
B12: GRANDES CONTAS
B13: GRUPO | C13: GRANDES CONTAS
E15: MÊS | F15: Valores
E16: ABRIL | H16: MAIO | K16: JUNHO | N16: JULHO | Q16: Total META | R16: Total R$ | S16: Total % R
B17: EQUIPE | C17: ID | D17: ÁREA | E17: META | F17: R$ | G17: % R | H17: META | I17: R$ | J17: % R | K17: META | L17: R$ | M17: % R | N17: META | O17: R$ | P17: % R
B18: FLP-SUL MC/KA D | C18: 224 | D18: KA-CRC PC | E18: 419840.91 | F18: 382686.02 | G18: 0.91150245 | H18: 1162636 | I18: 889738.63 | J18: 0.76527703 | K18: 549023 | L18: 675775.68 | M18: 1.2308695 | N18: 0 | Q18: 2131499.9 | R18: 1948200.3 | S18: 0.91400442
C19: 3861 | D19: MC-PLH PC | E19: 60765.15 | F19: 41409.1 | G19: 0.68146133 | H19: 168274 | I19: 176850.87 | J19: 1.0509697 | K19: 79462 | L19: 72678.28 | M19: 0.91462938 | N19: 0 | Q19: 308501.15 | R19: 290938.25 | S19: 0.94307023
B20: NORTE MC/KA D | C20: 179 | D20: KA-BRQ | E20: 68053.03 | F20: 128009.7 | G20: 1.8810287 | H20: 188456 | I20: 186605.8 | J20: 0.99018232 | K20: 88991 | L20: 45381.7 | M20: 0.50995831 | N20: 0 | Q20: 345500.03 | R20: 359997.2 | S20: 1.04196
B21: NORTE MC/KA M | C21: 417 | D21: KA-ROS | E21: 39393.94 | F21: 52563.46 | G21: 1.3343032 | H21: 109092 | I21: 95503.58 | J21: 0.87544073 | K21: 51515 | L21: 21184.49 | M21: 0.41122954 | N21: 0 | Q21: 200000.94 | R21: 169251.53 | S21: 0.84625367
C22: 5009 | D22: KA-BNU M | E22: 108333.33 | F22: 79964.61 | G22: 0.73813488 | H22: 300000 | I22: 369673.91 | J22: 1.2322464 | K22: 141667 | L22: 89730.68 | M22: 0.63339154 | N22: 0 | Q22: 550000.33 | R22: 539369.2 | S22: 0.98067068
B26: RANKING MÉDIAS CONTAS
B27: GRUPO | C27: MÉDIAS CONTAS
E29: MÊS | F29: Valores
E30: ABRIL | H30: MAIO | K30: JUNHO | N30: JULHO | Q30: Total META | R30: Total R$ | S30: Total % R | U30: MERCHANDISING | Z30: PONTUAÇÕES RANKING | AJ30: RANKING
B31: EQUIPE | C31: ID | D31: ÁREA | E31: META | F31: R$ | G31: % R | H31: META | I31: R$ | J31: % R | K31: META | L31: R$ | M31: % R | N31: META | O31: R$ | P31: % R | U31: BARRACA MONTADA | V31: PONTO EXTRA | W31: LINHA ZERO AÇUCAR | X31: LANÇAMENTOS | Z31: R$ ABRIL | AA31: R$ MAIO | AB31: R$ JUNHO | AC31: R$ JULHO | AD31: R$ TOTAL | AE31: BARRACA MONTADA | AF31: PONTO EXTRA | AG31: LINHA ZERO AÇUCAR | AH31: LANÇAMENTOS | AJ31: TOTAL | AK31: RANKING
B32: FLP-SUL MC/KA M | C32: 307 | D32: MC-ARA M | E32: 2856.06 | F32: 3163.19 | G32: 1.1075363 | H32: 7909 | I32: 23722.78 | J32: 2.9994664 | K32: 3735 | L32: 6169.57 | M32: 1.651826 | N32: 0 | Q32: 14500.06 | R32: 33055.54 | S32: 2.279683 | U32: =SUMIF(CLIENTES!$C:$C,'MÉDIAS CONTAS'!$C32,CLIENTES!$L:$L) -> 1 | V32: =SUMIF(CLIENTES!$C:$C,'MÉDIAS CONTAS'!$C32,CLIENTES!$M:$M) -> 1 | W32: =SUMIF(CLIENTES!$C:$C,'MÉDIAS CONTAS'!$C32,CLIENTES!$N:$N) -> 0 | X32: =SUMIF(CLIENTES!$C:$C,'MÉDIAS CONTAS'!$C32,CLIENTES!$O:$O) -> 0 | Z32: =IF(G32>=100%,2,0) -> 2 | AA32: =IF(J32>=100%,2,0) -> 2 | AB32: =IF(M32>=100%,2,0) -> 2 | AC32: =IF(P32>=100%,2,0) -> 0 | AD32: =IF(S32>=100%,2,0) -> 2 | AE32: =Tabela12[[#This Row],[BARRACA MONTADA]]*5 -> 5 | AF32: =Tabela12[[#This Row],[PONTO EXTRA]]*5 -> 5 | AG32: =Tabela12[[#This Row],[LINHA ZERO AÇUCAR]]*2 -> 0 | AH32: =Tabela12[[#This Row],[LANÇAMENTOS]]*3 -> 0 | AJ32: =SUM(Tabela13[#This Row]) -> 18 | AK32: =_xlfn.RANK.EQ(AJ32,$AJ$32:$AJ$44,0)& "º" -> 6º
C33: 383 | D33: MC-TBCR M | E33: 40575.76 | F33: 57361.39 | G33: 1.4136862 | H33: 112364 | I33: 106648.83 | J33: 0.949137 | K33: 53061 | L33: 31447.42 | M33: 0.59266542 | N33: 0 | Q33: 206000.76 | R33: 195457.64 | S33: 0.94881999 | U33: =SUMIF(CLIENTES!$C:$C,'MÉDIAS CONTAS'!$C33,CLIENTES!$L:$L) -> 0 | V33: =SUMIF(CLIENTES!$C:$C,'MÉDIAS CONTAS'!$C33,CLIENTES!$M:$M) -> 1 | W33: =SUMIF(CLIENTES!$C:$C,'MÉDIAS CONTAS'!$C33,CLIENTES!$N:$N) -> 0 | X33: =SUMIF(CLIENTES!$C:$C,'MÉDIAS CONTAS'!$C33,CLIENTES!$O:$O) -> 0 | Z33: =IF(G33>=100%,2,0) -> 2 | AA33: =IF(J33>=100%,2,0) -> 0 | AB33: =IF(M33>=100%,2,0) -> 0 | AC33: =IF(P33>=100%,2,0) -> 0 | AD33: =IF(S33>=100%,2,0) -> 0 | AE33: =Tabela12[[#This Row],[BARRACA MONTADA]]*5 -> 0 | AF33: =Tabela12[[#This Row],[PONTO EXTRA]]*5 -> 5 | AG33: =Tabela12[[#This Row],[LINHA ZERO AÇUCAR]]*2 -> 0 | AH33: =Tabela12[[#This Row],[LANÇAMENTOS]]*3 -> 0 | AJ33: =SUM(Tabela13[#This Row]) -> 7 | AK33: =_xlfn.RANK.EQ(AJ33,$AJ$32:$AJ$44,0)& "º" -> 9º
C34: 3928 | D34: MC-FLP M | E34: 12803.03 | F34: 13577.85 | G34: 1.0605185 | H34: 35455 | I34: 35927.8 | J34: 1.0133352 | K34: 16742 | L34: 5479.45 | M34: 0.32728766 | N34: 0 | Q34: 65000.03 | R34: 54985.1 | S34: 0.84592422 | U34: =SUMIF(CLIENTES!$C:$C,'MÉDIAS CONTAS'!$C34,CLIENTES!$L:$L) -> 0 | V34: =SUMIF(CLIENTES!$C:$C,'MÉDIAS CONTAS'!$C34,CLIENTES!$M:$M) -> 0 | W34: =SUMIF(CLIENTES!$C:$C,'MÉDIAS CONTAS'!$C34,CLIENTES!$N:$N) -> 0 | X34: =SUMIF(CLIENTES!$C:$C,'MÉDIAS CONTAS'!$C34,CLIENTES!$O:$O) -> 0 | Z34: =IF(G34>=100%,2,0) -> 2 | AA34: =IF(J34>=100%,2,0) -> 2 | AB34: =IF(M34>=100%,2,0) -> 0 | AC34: =IF(P34>=100%,2,0) -> 0 | AD34: =IF(S34>=100%,2,0) -> 0 | AE34: =Tabela12[[#This Row],[BARRACA MONTADA]]*5 -> 0 | AF34: =Tabela12[[#This Row],[PONTO EXTRA]]*5 -> 0 | AG34: =Tabela12[[#This Row],[LINHA ZERO AÇUCAR]]*2 -> 0 | AH34: =Tabela12[[#This Row],[LANÇAMENTOS]]*3 -> 0 | AJ34: =SUM(Tabela13[#This Row]) -> 4 | AK34: =_xlfn.RANK.EQ(AJ34,$AJ$32:$AJ$44,0)& "º" -> 12º
C35: 3942 | D35: MC-IMB M | E35: 9651.52 | F35: 29489.11 | G35: 3.0553851 | H35: 26727 | I35: 102442.89 | J35: 3.8329364 | K35: 12621 | L35: -2489.35 | M35: -0.19723873 | N35: 0 | Q35: 48999.52 | R35: 129442.65 | S35: 2.6417126 | U35: =SUMIF(CLIENTES!$C:$C,'MÉDIAS CONTAS'!$C35,CLIENTES!$L:$L) -> 12 | V35: =SUMIF(CLIENTES!$C:$C,'MÉDIAS CONTAS'!$C35,CLIENTES!$M:$M) -> 2 | W35: =SUMIF(CLIENTES!$C:$C,'MÉDIAS CONTAS'!$C35,CLIENTES!$N:$N) -> 0 | X35: =SUMIF(CLIENTES!$C:$C,'MÉDIAS CONTAS'!$C35,CLIENTES!$O:$O) -> 0 | Z35: =IF(G35>=100%,2,0) -> 2 | AA35: =IF(J35>=100%,2,0) -> 2 | AB35: =IF(M35>=100%,2,0) -> 0 | AC35: =IF(P35>=100%,2,0) -> 0 | AD35: =IF(S35>=100%,2,0) -> 2 | AE35: =Tabela12[[#This Row],[BARRACA MONTADA]]*5 -> 60 | AF35: =Tabela12[[#This Row],[PONTO EXTRA]]*5 -> 10 | AG35: =Tabela12[[#This Row],[LINHA ZERO AÇUCAR]]*2 -> 0 | AH35: =Tabela12[[#This Row],[LANÇAMENTOS]]*3 -> 0 | AJ35: =SUM(Tabela13[#This Row]) -> 76 | AK35: =_xlfn.RANK.EQ(AJ35,$AJ$32:$AJ$44,0)& "º" -> 1º
C36: 4056 | D36: MC-SJO M | E36: 9848.48 | F36: 4997.84 | G36: 0.50747323 | H36: 27273 | I36: 7899.85 | J36: 0.28965827 | K36: 12879 | L36: 13795.64 | M36: 1.0711732 | N36: 0 | Q36: 50000.48 | R36: 26693.33 | S36: 0.53386147 | U36: =SUMIF(CLIENTES!$C:$C,'MÉDIAS CONTAS'!$C36,CLIENTES!$L:$L) -> 3 | V36: =SUMIF(CLIENTES!$C:$C,'MÉDIAS CONTAS'!$C36,CLIENTES!$M:$M) -> 0 | W36: =SUMIF(CLIENTES!$C:$C,'MÉDIAS CONTAS'!$C36,CLIENTES!$N:$N) -> 0 | X36: =SUMIF(CLIENTES!$C:$C,'MÉDIAS CONTAS'!$C36,CLIENTES!$O:$O) -> 0 | Z36: =IF(G36>=100%,2,0) -> 0 | AA36: =IF(J36>=100%,2,0) -> 0 | AB36: =IF(M36>=100%,2,0) -> 2 | AC36: =IF(P36>=100%,2,0) -> 0 | AD36: =IF(S36>=100%,2,0) -> 0 | AE36: =Tabela12[[#This Row],[BARRACA MONTADA]]*5 -> 15 | AF36: =Tabela12[[#This Row],[PONTO EXTRA]]*5 -> 0 | AG36: =Tabela12[[#This Row],[LINHA ZERO AÇUCAR]]*2 -> 0 | AH36: =Tabela12[[#This Row],[LANÇAMENTOS]]*3 -> 0 | AJ36: =SUM(Tabela13[#This Row]) -> 17 | AK36: =_xlfn.RANK.EQ(AJ36,$AJ$32:$AJ$44,0)& "º" -> 7º
C37: 4065 | D37: MC-LAGES | E37: 10340.91 | F37: 11804.28 | G37: 1.1415127 | H37: 28636 | I37: 27567.37 | J37: 0.96268229 | K37: 13523 | L37: 12256.15 | M37: 0.90631886 | N37: 0 | Q37: 52499.91 | R37: 51627.8 | S37: 0.98338835 | U37: =SUMIF(CLIENTES!$C:$C,'MÉDIAS CONTAS'!$C37,CLIENTES!$L:$L) -> 2 | V37: =SUMIF(CLIENTES!$C:$C,'MÉDIAS CONTAS'!$C37,CLIENTES!$M:$M) -> 0 | W37: =SUMIF(CLIENTES!$C:$C,'MÉDIAS CONTAS'!$C37,CLIENTES!$N:$N) -> 0 | X37: =SUMIF(CLIENTES!$C:$C,'MÉDIAS CONTAS'!$C37,CLIENTES!$O:$O) -> 0 | Z37: =IF(G37>=100%,2,0) -> 2 | AA37: =IF(J37>=100%,2,0) -> 0 | AB37: =IF(M37>=100%,2,0) -> 0 | AC37: =IF(P37>=100%,2,0) -> 0 | AD37: =IF(S37>=100%,2,0) -> 0 | AE37: =Tabela12[[#This Row],[BARRACA MONTADA]]*5 -> 10 | AF37: =Tabela12[[#This Row],[PONTO EXTRA]]*5 -> 0 | AG37: =Tabela12[[#This Row],[LINHA ZERO AÇUCAR]]*2 -> 0 | AH37: =Tabela12[[#This Row],[LANÇAMENTOS]]*3 -> 0 | AJ37: =SUM(Tabela13[#This Row]) -> 12 | AK37: =_xlfn.RANK.EQ(AJ37,$AJ$32:$AJ$44,0)& "º" -> 8º
C38: 4085 | D38: MC-CRC M | E38: 6500 | F38: 12098.36 | G38: 1.8612862 | H38: 18000 | I38: 14189.82 | J38: 0.78832333 | K38: 8500 | L38: 8869.07 | M38: 1.04342 | N38: 0 | Q38: 33000 | R38: 35157.25 | S38: 1.0653712 | U38: =SUMIF(CLIENTES!$C:$C,'MÉDIAS CONTAS'!$C38,CLIENTES!$L:$L) -> 0 | V38: =SUMIF(CLIENTES!$C:$C,'MÉDIAS CONTAS'!$C38,CLIENTES!$M:$M) -> 0 | W38: =SUMIF(CLIENTES!$C:$C,'MÉDIAS CONTAS'!$C38,CLIENTES!$N:$N) -> 0 | X38: =SUMIF(CLIENTES!$C:$C,'MÉDIAS CONTAS'!$C38,CLIENTES!$O:$O) -> 0 | Z38: =IF(G38>=100%,2,0) -> 2 | AA38: =IF(J38>=100%,2,0) -> 0 | AB38: =IF(M38>=100%,2,0) -> 2 | AC38: =IF(P38>=100%,2,0) -> 0 | AD38: =IF(S38>=100%,2,0) -> 2 | AE38: =Tabela12[[#This Row],[BARRACA MONTADA]]*5 -> 0 | AF38: =Tabela12[[#This Row],[PONTO EXTRA]]*5 -> 0 | AG38: =Tabela12[[#This Row],[LINHA ZERO AÇUCAR]]*2 -> 0 | AH38: =Tabela12[[#This Row],[LANÇAMENTOS]]*3 -> 0 | AJ38: =SUM(Tabela13[#This Row]) -> 6 | AK38: =_xlfn.RANK.EQ(AJ38,$AJ$32:$AJ$44,0)& "º" -> 10º
C39: 5005 | D39: MC-BGU M | E39: 9946.97 | F39: 7377.42 | G39: 0.7416751 | H39: 27545 | I39: 64096.83 | J39: 2.326986 | K39: 13008 | L39: 13882.88 | M39: 1.0672571 | N39: 0 | Q39: 50499.97 | R39: 85357.13 | S39: 1.6902412 | U39: =SUMIF(CLIENTES!$C:$C,'MÉDIAS CONTAS'!$C39,CLIENTES!$L:$L) -> 5 | V39: =SUMIF(CLIENTES!$C:$C,'MÉDIAS CONTAS'!$C39,CLIENTES!$M:$M) -> 0 | W39: =SUMIF(CLIENTES!$C:$C,'MÉDIAS CONTAS'!$C39,CLIENTES!$N:$N) -> 0 | X39: =SUMIF(CLIENTES!$C:$C,'MÉDIAS CONTAS'!$C39,CLIENTES!$O:$O) -> 0 | Z39: =IF(G39>=100%,2,0) -> 0 | AA39: =IF(J39>=100%,2,0) -> 2 | AB39: =IF(M39>=100%,2,0) -> 2 | AC39: =IF(P39>=100%,2,0) -> 0 | AD39: =IF(S39>=100%,2,0) -> 2 | AE39: =Tabela12[[#This Row],[BARRACA MONTADA]]*5 -> 25 | AF39: =Tabela12[[#This Row],[PONTO EXTRA]]*5 -> 0 | AG39: =Tabela12[[#This Row],[LINHA ZERO AÇUCAR]]*2 -> 0 | AH39: =Tabela12[[#This Row],[LANÇAMENTOS]]*3 -> 0 | AJ39: =SUM(Tabela13[#This Row]) -> 31 | AK39: =_xlfn.RANK.EQ(AJ39,$AJ$32:$AJ$44,0)& "º" -> 4º
B40: NORTE MC/KA M | C40: 683 | D40: MC-ITPE M | E40: 27772.73 | F40: 8345.14 | G40: 0.30047964 | H40: 76909 | I40: 55580.23 | J40: 0.72267524 | K40: 36318 | L40: 12329.26 | M40: 0.3394807 | N40: 0 | Q40: 140999.73 | R40: 76254.63 | S40: 0.54081401 | U40: =SUMIF(CLIENTES!$C:$C,'MÉDIAS CONTAS'!$C40,CLIENTES!$L:$L) -> 2 | V40: =SUMIF(CLIENTES!$C:$C,'MÉDIAS CONTAS'!$C40,CLIENTES!$M:$M) -> 4 | W40: =SUMIF(CLIENTES!$C:$C,'MÉDIAS CONTAS'!$C40,CLIENTES!$N:$N) -> 0 | X40: =SUMIF(CLIENTES!$C:$C,'MÉDIAS CONTAS'!$C40,CLIENTES!$O:$O) -> 0 | Z40: =IF(G40>=100%,2,0) -> 0 | AA40: =IF(J40>=100%,2,0) -> 0 | AB40: =IF(M40>=100%,2,0) -> 0 | AC40: =IF(P40>=100%,2,0) -> 0 | AD40: =IF(S40>=100%,2,0) -> 0 | AE40: =Tabela12[[#This Row],[BARRACA MONTADA]]*5 -> 10 | AF40: =Tabela12[[#This Row],[PONTO EXTRA]]*5 -> 20 | AG40: =Tabela12[[#This Row],[LINHA ZERO AÇUCAR]]*2 -> 0 | AH40: =Tabela12[[#This Row],[LANÇAMENTOS]]*3 -> 0 | AJ40: =SUM(Tabela13[#This Row]) -> 30 | AK40: =_xlfn.RANK.EQ(AJ40,$AJ$32:$AJ$44,0)& "º" -> 5º
C41: 3147 | D41: MC-BNU M | E41: 9848.48 | F41: 4810.43 | G41: 0.4884439 | H41: 27273 | I41: 11396.51 | J41: 0.41786785 | K41: 12879 | L41: 964.5 | M41: 0.074889355 | N41: 0 | Q41: 50000.48 | R41: 17171.44 | S41: 0.3434255 | U41: =SUMIF(CLIENTES!$C:$C,'MÉDIAS CONTAS'!$C41,CLIENTES!$L:$L) -> 1 | V41: =SUMIF(CLIENTES!$C:$C,'MÉDIAS CONTAS'!$C41,CLIENTES!$M:$M) -> 0 | W41: =SUMIF(CLIENTES!$C:$C,'MÉDIAS CONTAS'!$C41,CLIENTES!$N:$N) -> 0 | X41: =SUMIF(CLIENTES!$C:$C,'MÉDIAS CONTAS'!$C41,CLIENTES!$O:$O) -> 0 | Z41: =IF(G41>=100%,2,0) -> 0 | AA41: =IF(J41>=100%,2,0) -> 0 | AB41: =IF(M41>=100%,2,0) -> 0 | AC41: =IF(P41>=100%,2,0) -> 0 | AD41: =IF(S41>=100%,2,0) -> 0 | AE41: =Tabela12[[#This Row],[BARRACA MONTADA]]*5 -> 5 | AF41: =Tabela12[[#This Row],[PONTO EXTRA]]*5 -> 0 | AG41: =Tabela12[[#This Row],[LINHA ZERO AÇUCAR]]*2 -> 0 | AH41: =Tabela12[[#This Row],[LANÇAMENTOS]]*3 -> 0 | AJ41: =SUM(Tabela13[#This Row]) -> 5 | AK41: =_xlfn.RANK.EQ(AJ41,$AJ$32:$AJ$44,0)& "º" -> 11º
C42: 3221 | D42: MC-JLLE M | E42: 29545.45 | F42: 12598.06 | G42: 0.42639594 | H42: 81818 | I42: 38149.06 | J42: 0.46626733 | K42: 38636 | L42: 10852.02 | M42: 0.28087846 | N42: 0 | Q42: 149999.45 | R42: 61599.14 | S42: 0.41066244 | U42: =SUMIF(CLIENTES!$C:$C,'MÉDIAS CONTAS'!$C42,CLIENTES!$L:$L) -> 0 | V42: =SUMIF(CLIENTES!$C:$C,'MÉDIAS CONTAS'!$C42,CLIENTES!$M:$M) -> 0 | W42: =SUMIF(CLIENTES!$C:$C,'MÉDIAS CONTAS'!$C42,CLIENTES!$N:$N) -> 0 | X42: =SUMIF(CLIENTES!$C:$C,'MÉDIAS CONTAS'!$C42,CLIENTES!$O:$O) -> 0 | Z42: =IF(G42>=100%,2,0) -> 0 | AA42: =IF(J42>=100%,2,0) -> 0 | AB42: =IF(M42>=100%,2,0) -> 0 | AC42: =IF(P42>=100%,2,0) -> 0 | AD42: =IF(S42>=100%,2,0) -> 0 | AE42: =Tabela12[[#This Row],[BARRACA MONTADA]]*5 -> 0 | AF42: =Tabela12[[#This Row],[PONTO EXTRA]]*5 -> 0 | AG42: =Tabela12[[#This Row],[LINHA ZERO AÇUCAR]]*2 -> 0 | AH42: =Tabela12[[#This Row],[LANÇAMENTOS]]*3 -> 0 | AJ42: =SUM(Tabela13[#This Row]) -> 0 | AK42: =_xlfn.RANK.EQ(AJ42,$AJ$32:$AJ$44,0)& "º" -> 13º
C43: 4067 | D43: MC-ITJ M | E43: 22651.52 | F43: 13030.89 | G43: 0.57527663 | H43: 62727 | I43: 67152.1 | J43: 1.0705454 | K43: 29621 | L43: 18524.67 | M43: 0.62538976 | N43: 0 | Q43: 114999.52 | R43: 98707.66 | S43: 0.85833106 | U43: =SUMIF(CLIENTES!$C:$C,'MÉDIAS CONTAS'!$C43,CLIENTES!$L:$L) -> 11 | V43: =SUMIF(CLIENTES!$C:$C,'MÉDIAS CONTAS'!$C43,CLIENTES!$M:$M) -> 0 | W43: =SUMIF(CLIENTES!$C:$C,'MÉDIAS CONTAS'!$C43,CLIENTES!$N:$N) -> 0 | X43: =SUMIF(CLIENTES!$C:$C,'MÉDIAS CONTAS'!$C43,CLIENTES!$O:$O) -> 0 | Z43: =IF(G43>=100%,2,0) -> 0 | AA43: =IF(J43>=100%,2,0) -> 2 | AB43: =IF(M43>=100%,2,0) -> 0 | AC43: =IF(P43>=100%,2,0) -> 0 | AD43: =IF(S43>=100%,2,0) -> 0 | AE43: =Tabela12[[#This Row],[BARRACA MONTADA]]*5 -> 55 | AF43: =Tabela12[[#This Row],[PONTO EXTRA]]*5 -> 0 | AG43: =Tabela12[[#This Row],[LINHA ZERO AÇUCAR]]*2 -> 0 | AH43: =Tabela12[[#This Row],[LANÇAMENTOS]]*3 -> 0 | AJ43: =SUM(Tabela13[#This Row]) -> 57 | AK43: =_xlfn.RANK.EQ(AJ43,$AJ$32:$AJ$44,0)& "º" -> 2º
C44: 4096 | D44: MC-SFS M | E44: 10833.33 | F44: 12336.67 | G44: 1.1387699 | H44: 30000 | I44: 43961.89 | J44: 1.4653963 | K44: 14167 | L44: -23.04 | M44: -0.0016263147 | N44: 0 | Q44: 55000.33 | R44: 56275.52 | S44: 1.0231851 | U44: =SUMIF(CLIENTES!$C:$C,'MÉDIAS CONTAS'!$C44,CLIENTES!$L:$L) -> 7 | V44: =SUMIF(CLIENTES!$C:$C,'MÉDIAS CONTAS'!$C44,CLIENTES!$M:$M) -> 0 | W44: =SUMIF(CLIENTES!$C:$C,'MÉDIAS CONTAS'!$C44,CLIENTES!$N:$N) -> 0 | X44: =SUMIF(CLIENTES!$C:$C,'MÉDIAS CONTAS'!$C44,CLIENTES!$O:$O) -> 0 | Z44: =IF(G44>=100%,2,0) -> 2 | AA44: =IF(J44>=100%,2,0) -> 2 | AB44: =IF(M44>=100%,2,0) -> 0 | AC44: =IF(P44>=100%,2,0) -> 0 | AD44: =IF(S44>=100%,2,0) -> 2 | AE44: =Tabela12[[#This Row],[BARRACA MONTADA]]*5 -> 35 | AF44: =Tabela12[[#This Row],[PONTO EXTRA]]*5 -> 0 | AG44: =Tabela12[[#This Row],[LINHA ZERO AÇUCAR]]*2 -> 0 | AH44: =Tabela12[[#This Row],[LANÇAMENTOS]]*3 -> 0 | AJ44: =SUM(Tabela13[#This Row]) -> 41 | AK44: =_xlfn.RANK.EQ(AJ44,$AJ$32:$AJ$44,0)& "º" -> 3º

Sheet CLIENTES
B3: EQUIPE | C3: CÓD | D3: ÁREA | E3: CÓD | F3: RAZÃO | G3: DIA | H3: DATA | I3: POSITIVAÇÃO GERAL | J3: PAÇOCA ZERO | K3: LANÇAMENTOS | L3: BARRACAS(FOTO) | M3: P.EXTRAS(FOTO) | N3: LINHA ZERO(BARRACA) | O3: LANÇAMENTOS(BARRACA)
B4: FLORIPA M | C4: 4026 | D4: FLP-CONV-ILHA | E4: 52245 | F4: POSTO GALO LTDA | G4: Qua | H4: 46176 | I4: 1 | J4: 1
B5: FLORIPA M | C5: 4026 | D5: FLP-CONV-ILHA | E5: 52247 | F5: LS COM SORVETE BOMBONIERE E TABAC LTDA | G5: Sex | H5: 46171
B6: FLORIPA M | C6: 4026 | D6: FLP-CONV-ILHA | E6: 52381 | F6: POSTO GALO LTDA | G6: Ter | H6: 46182 | I6: 1
B7: FLORIPA M | C7: 4026 | D7: FLP-CONV-ILHA | E7: 53111 | F7: CIDINEI JOAO DE SOUZA | G7: Qui | H7: 46170 | I7: 1
B8: FLORIPA M | C8: 4026 | D8: FLP-CONV-ILHA | E8: 55988 | F8: M R MACHADO E CIA LTDA | G8: Qui | H8: 46177
B9: FLORIPA M | C9: 4026 | D9: FLP-CONV-ILHA | E9: 61579 | F9: DM COMERCIO DE ALIMENTOS LTDA | G9: Sex | H9: 46171
B10: FLORIPA M | C10: 4026 | D10: FLP-CONV-ILHA | E10: 62492 | F10: POSTO GALO LTDA | G10: Qua | H10: 46183 | I10: 1
B11: FLORIPA M | C11: 4026 | D11: FLP-CONV-ILHA | E11: 63694 | F11: RESTAURANTE MEDEIROS LTDA | G11: Sex | H11: 46171
B12: FLORIPA M | C12: 4026 | D12: FLP-CONV-ILHA | E12: 66820 | F12: COLONIAL PRODUTOS SERVICOS LTDA | G12: Ter | H12: 46182 | I12: 1
B13: FLORIPA M | C13: 4026 | D13: FLP-CONV-ILHA | E13: 66834 | F13: POSTO GALO LTDA | G13: Qua | H13: 46183 | I13: 1 | J13: 1
B14: FLORIPA M | C14: 4026 | D14: FLP-CONV-ILHA | E14: 67800 | F14: POSTO RIO VERMELHO LTDA | G14: Seg | H14: 46181
B15: FLORIPA M | C15: 4026 | D15: FLP-CONV-ILHA | E15: 69981 | F15: POSTO MARILU LTDA | G15: Seg | H15: 46181
B16: FLORIPA M | C16: 4026 | D16: FLP-CONV-ILHA | E16: 73333 | F16: POSTO RIO VERMELHO LTDA | G16: Seg | H16: 46181
B17: FLORIPA M | C17: 4026 | D17: FLP-CONV-ILHA | E17: 74157 | F17: AVILA COMERCIO DE COMBUSTIVEIS LTDA | G17: Qua | H17: 46176
B18: FLORIPA M | C18: 4026 | D18: FLP-CONV-ILHA | E18: 74763 | F18: VILA RICA COMERCIO DE COMBUSTIVEIS LTDA | G18: Ter | H18: 46182
B19: FLORIPA M | C19: 4026 | D19: FLP-CONV-ILHA | E19: 74844 | F19: COMERCIO DE COMB E LUBRIF INGLESES LTDA | G19: Seg | H19: 46181 | I19: 1
B20: FLORIPA M | C20: 4026 | D20: FLP-CONV-ILHA | E20: 77041 | F20: POSTO GALO LTDA | G20: Ter | H20: 46175 | I20: 1 | J20: 1
B21: FLORIPA M | C21: 4026 | D21: FLP-CONV-ILHA | E21: 77452 | F21: POSTO GALO LTDA | G21: Ter | H21: 46175 | I21: 1 | J21: 1
B22: FLORIPA M | C22: 4026 | D22: FLP-CONV-ILHA | E22: 78038 | F22: POSTO DE SERVICOS ILHA BELA LTDA | G22: Ter | H22: 46182 | I22: 1 | J22: 1
B23: FLORIPA M | C23: 4026 | D23: FLP-CONV-ILHA | E23: 78751 | F23: AUTO POSTO ABAST E SERV 5 ESTRELAS LTDA | G23: Ter | H23: 46182
B24: FLORIPA M | C24: 4026 | D24: FLP-CONV-ILHA | E24: 80510 | F24: VALPAS BOMBONIERE E TABACARIA LTDA | G24: Seg | H24: 46174 | I24: 1
B25: FLORIPA M | C25: 4026 | D25: FLP-CONV-ILHA | E25: 82816 | F25: REAL AUTO POSTO LTDA | G25: Qui | H25: 46170
B26: FLORIPA M | C26: 4026 | D26: FLP-CONV-ILHA | E26: 83279 | F26: FLORIPETRO COM DE COMBUSTIVEIS LTDA | G26: Ter | H26: 46182 | I26: 1 | J26: 1
B27: FLORIPA M | C27: 4026 | D27: FLP-CONV-ILHA | E27: 83948 | F27: NEI SARTOR ME | G27: Qui | H27: 46177
B28: FLORIPA M | C28: 4026 | D28: FLP-CONV-ILHA | E28: 84056 | F28: DELICIAS DO CAMPO LTDA | G28: Qua | H28: 46183
B29: FLORIPA M | C29: 4026 | D29: FLP-CONV-ILHA | E29: 84396 | F29: LANCHONETE DANDARA MEDEIROS LTDA | G29: Sex | H29: 46171
B30: FLORIPA M | C30: 4026 | D30: FLP-CONV-ILHA | E30: 86129 | F30: MANOEL JERUSALEM DA SILVA SOARES | G30: Qui | H30: 46177 | I30: 1
B31: FLORIPA M | C31: 4026 | D31: FLP-CONV-ILHA | E31: 87204 | F31: COMERCIO DE LANCHES DEODORO LTDA | G31: Sex | H31: 46171
B32: FLORIPA M | C32: 4026 | D32: FLP-CONV-ILHA | E32: 88228 | F32: BADOFE LANCHES LTDA | G32: Sex | H32: 46171
B33: FLORIPA M | C33: 4026 | D33: FLP-CONV-ILHA | E33: 88559 | F33: FABIMAR LANCHES LTDA | G33: Qui | H33: 46177
B34: FLORIPA M | C34: 4026 | D34: FLP-CONV-ILHA | E34: 90701 | F34: CARIONI COMERCIO VAREJISTA DE COMB LTDA | G34: Qui | H34: 46170
B35: FLORIPA M | C35: 4026 | D35: FLP-CONV-ILHA | E35: 92163 | F35: MR. CHICO FOOD LTDA | G35: Seg | H35: 46174
B36: FLORIPA M | C36: 4026 | D36: FLP-CONV-ILHA | E36: 93212 | F36: RZR COMERCIO DE COMBUSTIVEIS LTDA | G36: Qua | H36: 46176 | I36: 1
B37: FLORIPA M | C37: 4026 | D37: FLP-CONV-ILHA | E37: 95971 | F37: POSTO GALO LTDA | G37: Ter | H37: 46175
B38: FLORIPA M | C38: 4026 | D38: FLP-CONV-ILHA | E38: 96586 | F38: RKZ COMERCIO DE COMBUSTIVEIS LTDA | G38: Qua | H38: 46176 | I38: 1
B39: FLORIPA M | C39: 4026 | D39: FLP-CONV-ILHA | E39: 98186 | F39: SAVI RESTAURANTE E LANCHONETE LTDA | G39: Sex | H39: 46171
B40: FLORIPA M | C40: 4026 | D40: FLP-CONV-ILHA | E40: 98749 | F40: LOJA DE CONVENIENCIAS FLORIPA LTDA | G40: Qua | H40: 46183
B41: FLORIPA M | C41: 4026 | D41: FLP-CONV-ILHA | E41: 99565 | F41: MARCLA COMERCIO DE ALIMENTOS LTDA | G41: Qui | H41: 46177
B42: FLORIPA M | C42: 4026 | D42: FLP-CONV-ILHA | E42: 99582 | F42: MDESTRI COMBUSTIVEIS E LUBRIFICANTES LTDA | G42: Ter | H42: 46182
B43: FLORIPA M | C43: 4026 | D43: FLP-CONV-ILHA | E43: 100871 | F43: GOLDEN COM DE COMBUSTIVEIS LTDA | G43: Sex | H43: 46178
B44: FLORIPA M | C44: 4026 | D44: FLP-CONV-ILHA | E44: 101128 | F44: HOTELARIA ACCOR BRASIL S A | G44: Qua | H44: 46183
B45: FLORIPA M | C45: 4026 | D45: FLP-CONV-ILHA | E45: 102352 | F45: POSTO CORREGO GRANDE LTDA | G45: Qui | H45: 46170
B46: FLORIPA M | C46: 4026 | D46: FLP-CONV-ILHA | E46: 103593 | F46: AUTO POSTO NOVO CAMPECHE LTDA | G46: Qua | H46: 46176 | I46: 1 | J46: 1 | K46: 1
B47: FLORIPA M | C47: 4026 | D47: FLP-CONV-ILHA | E47: 105715 | F47: CAMARAO LOJA DE CONVENIENCIA LTDA | G47: Qua | H47: 46176 | I47: 1 | J47: 1
B48: FLORIPA M | C48: 4026 | D48: FLP-CONV-ILHA | E48: 109691 | F48: AUTO POSTO TORNEG LTDA | G48: Seg | H48: 46181
B49: FLORIPA M | C49: 4026 | D49: FLP-CONV-ILHA | E49: 111369 | F49: ORLANDO JOAO TOMAZ LTDA | G49: Qui | H49: 46170
B50: FLORIPA M | C50: 4026 | D50: FLP-CONV-ILHA | E50: 111618 | F50: POSTO GALO LTDA | G50: Qua | H50: 46183 | I50: 1 | J50: 1
B51: FLORIPA M | C51: 4026 | D51: FLP-CONV-ILHA | E51: 114982 | F51: POSTO GALO LTDA | G51: Ter | H51: 46182 | I51: 1 | J51: 1
B52: FLORIPA M | C52: 4026 | D52: FLP-CONV-ILHA | E52: 115975 | F52: CAJUMA VARIEDADES LTDA | G52: Seg | H52: 46174
B53: FLORIPA M | C53: 4026 | D53: FLP-CONV-ILHA | E53: 116380 | F53: COMERCIO DE COMB E LUBRIF ASSUNCAO LTDA | G53: Sex | H53: 46178 | I53: 1
B54: FLORIPA M | C54: 4026 | D54: FLP-CONV-ILHA | E54: 117168 | F54: LANCHONETE GALERIA JAQUELINE LTDA | G54: Qui | H54: 46177 | I54: 1
B55: FLORIPA M | C55: 4026 | D55: FLP-CONV-ILHA | E55: 124395 | F55: AGPS HOTELARIA LTDA | G55: Qui | H55: 46177
B56: FLORIPA M | C56: 4026 | D56: FLP-CONV-ILHA | E56: 126548 | F56: POSTO DE COMBUSTIVEIS 401 EIRELI | G56: Qua | H56: 46183
B57: FLORIPA M | C57: 4026 | D57: FLP-CONV-ILHA | E57: 127766 | F57: COM DE COMB E DERV DE PETROLEO CACUPE LTDA | G57: Qua | H57: 46183 | I57: 1
B58: FLORIPA M | C58: 4026 | D58: FLP-CONV-ILHA | E58: 129876 | F58: A ANGELONI E CIA LTDA | G58: Ter | H58: 46175 | I58: 1 | J58: 1
B59: FLORIPA M | C59: 4026 | D59: FLP-CONV-ILHA | E59: 134770 | F59: RG LANCHONETE LTDA | G59: Qui | H59: 46177
B60: FLORIPA M | C60: 4026 | D60: FLP-CONV-ILHA | E60: 134911 | F60: CACULA COMERCIO DE MEDICAMENTOS LTDA | G60: Sex | H60: 46171
B61: FLORIPA M | C61: 4026 | D61: FLP-CONV-ILHA | E61: 134927 | F61: CANTO AZUL RESTAURANTE LTDA | G61: Qui | H61: 46177
B62: FLORIPA M | C62: 4026 | D62: FLP-CONV-ILHA | E62: 135942 | F62: FORNERIA LENHA E OLIVA COM DE ALIMENTOS LTDA | G62: Qui | H62: 46170
B63: FLORIPA M | C63: 4026 | D63: FLP-CONV-ILHA | E63: 138393 | F63: POSTO PARQUE SAO JORGE LTDA | G63: Qua | H63: 46183
B64: FLORIPA M | C64: 4026 | D64: FLP-CONV-ILHA | E64: 138424 | F64: LISBOA E LISBOA LANCHONETE LTDA | G64: Sex | H64: 46171
B65: FLORIPA M | C65: 4026 | D65: FLP-CONV-ILHA | E65: 139032 | F65: RA LANCHONETE LTDA | G65: Sex | H65: 46171
B66: FLORIPA M | C66: 4026 | D66: FLP-CONV-ILHA | E66: 140334 | F66: CASSOL MATERIAIS DE CONSTRUCAO LTDA FL01 | G66: Ter | H66: 46175
B67: FLORIPA M | C67: 4026 | D67: FLP-CONV-ILHA | E67: 141302 | F67: A ANGELONI E CIA LTDA | G67: Ter | H67: 46175 | I67: 1 | J67: 1
B68: FLORIPA M | C68: 4026 | D68: FLP-CONV-ILHA | E68: 143463 | F68: CONSTANTE E SANTOS RESTAURANTE LTDA | G68: Qui | H68: 46177 | I68: 1 | J68: 1 | K68: 1
B69: FLORIPA M | C69: 4026 | D69: FLP-CONV-ILHA | E69: 143478 | F69: A ANGELONI E CIA LTDA | G69: Qui | H69: 46170 | I69: 1 | J69: 1
B70: FLORIPA M | C70: 4026 | D70: FLP-CONV-ILHA | E70: 144269 | F70: AUTO POSTO JURERE LTDA | G70: Sex | H70: 46178 | I70: 1 | J70: 1
B71: FLORIPA M | C71: 4026 | D71: FLP-CONV-ILHA | E71: 144308 | F71: CONQUILHA RESTAURANTE EIRELI | G71: Ter | H71: 46182
B72: FLORIPA M | C72: 4026 | D72: FLP-CONV-ILHA | E72: 145355 | F72: POSTO AVENIDA LTDA | G72: Qui | H72: 46170
B73: FLORIPA M | C73: 4026 | D73: FLP-CONV-ILHA | E73: 146686 | F73: LANCHES E SORVETES TICEN LTDA | G73: Seg | H73: 46174
B74: FLORIPA M | C74: 4026 | D74: FLP-CONV-ILHA | E74: 146771 | F74: RSM LANCHONETE LTDA | G74: Seg | H74: 46174
B75: FLORIPA M | C75: 4026 | D75: FLP-CONV-ILHA | E75: 146961 | F75: LANCHONETE FELIPE SCHMIDT LTDA | G75: Qui | H75: 46177 | I75: 1
B76: FLORIPA M | C76: 4026 | D76: FLP-CONV-ILHA | E76: 147936 | F76: FABIANO BERTO DA SILVEIRA | G76: Seg | H76: 46174
B77: FLORIPA M | C77: 4026 | D77: FLP-CONV-ILHA | E77: 148183 | F77: CAFE OUTONO | G77: Qui | H77: 46177
B78: FLORIPA M | C78: 4026 | D78: FLP-CONV-ILHA | E78: 151531 | F78: AURINO DA SILVEIRA E CIA LTDA | G78: Sex | H78: 46171
B79: FLORIPA M | C79: 4026 | D79: FLP-CONV-ILHA | E79: 152823 | F79: MOMA EIRELI | G79: Ter | H79: 46182
B80: FLORIPA M | C80: 4026 | D80: FLP-CONV-ILHA | E80: 153700 | F80: ALINE VIEIRA FELICIANO ME | G80: Qui | H80: 46177
B81: FLORIPA M | C81: 4026 | D81: FLP-CONV-ILHA | E81: 154480 | F81: POSTO GALO LTDA | G81: Ter | H81: 46175
B82: FLORIPA M | C82: 4026 | D82: FLP-CONV-ILHA | E82: 154508 | F82: CAMPECHE COMERCIO COMBUSTIVES LTDA | G82: Qua | H82: 46176
B83: FLORIPA M | C83: 4026 | D83: FLP-CONV-ILHA | E83: 154589 | F83: COMERCIO DE COMBUSTIVEIS SPILLERE LTDA | G83: Qua | H83: 46183
B84: FLORIPA M | C84: 4026 | D84: FLP-CONV-ILHA | E84: 155784 | F84: CASSOL MATERIAIS DE CONSTRUCAO LTDA FL19 | G84: Ter | H84: 46175
B85: FLORIPA M | C85: 4026 | D85: FLP-CONV-ILHA | E85: 156080 | F85: SERV DE ONCOLOGIA MEDICA MAIS TRATAMENTO | G85: Sex | H85: 46171
B86: FLORIPA M | C86: 4026 | D86: FLP-CONV-ILHA | E86: 158319 | F86: RAFAEL EUCLIDES DAMASCO | G86: Seg | H86: 46174
B87: FLORIPA M | C87: 4026 | D87: FLP-CONV-ILHA | E87: 158635 | F87: SOLANAS COMERCIO DE COMBUSTIVEIS LTDA | G87: Seg | H87: 46181
B88: FLORIPA M | C88: 4026 | D88: FLP-CONV-ILHA | E88: 163980 | F88: FLEX HOTELARIA LTDA | G88: Seg | H88: 46174
B89: FLORIPA M | C89: 4026 | D89: FLP-CONV-ILHA | E89: 164406 | F89: EMPORIO MARTINS LTDA | G89: Seg | H89: 46174 | I89: 1
B90: FLORIPA M | C90: 4026 | D90: FLP-CONV-ILHA | E90: 165893 | F90: AUTO POSTO MONTE VERDE LTDA | G90: Qua | H90: 46183 | I90: 1
B91: FLORIPA M | C91: 4026 | D91: FLP-CONV-ILHA | E91: 167616 | F91: CASSOL MATERIAIS DE CONSTRUCAO LTDA FL20 | G91: Ter | H91: 46175
B92: FLORIPA M | C92: 4026 | D92: FLP-CONV-ILHA | E92: 167617 | F92: CASSOL MATERIAIS DE CONSTRUCAO LTDA FL25 | G92: Ter | H92: 46175
B93: FLORIPA M | C93: 4026 | D93: FLP-CONV-ILHA | E93: 168216 | F93: POSTO SANTO ANTONIO DE LISBOA LTDA | G93: Qua | H93: 46183
B94: FLORIPA M | C94: 4026 | D94: FLP-CONV-ILHA | E94: 168797 | F94: POSTO GALO LTDA | G94: Ter | H94: 46175 | I94: 1 | J94: 1
B95: FLORIPA M | C95: 4026 | D95: FLP-CONV-ILHA | E95: 171485 | F95: SLAVIERO EMPREENDIMENTOS HOTELEIROS LTDA | G95: Seg | H95: 46174
B96: FLORIPA M | C96: 4026 | D96: FLP-CONV-ILHA | E96: 171620 | F96: GISLAINE BERNARDO TOMAZ PEREIRA E CIA LTDA | G96: Qui | H96: 46170 | I96: 1
B97: FLORIPA M | C97: 4026 | D97: FLP-CONV-ILHA | E97: 171726 | F97: PALADAR ALIMENTOS E BEBIDAS LTDA | G97: Sex | H97: 46171
B98: FLORIPA M | C98: 4026 | D98: FLP-CONV-ILHA | E98: 171956 | F98: INGLESES COMERCIO DE COMBUSTIVEL LTDA | G98: Seg | H98: 46181 | I98: 1 | J98: 1
B99: FLORIPA M | C99: 4026 | D99: FLP-CONV-ILHA | E99: 172325 | F99: LOJA DO POXTO 24 HS LTDA | G99: Qui | H99: 46170 | I99: 1 | J99: 1
B100: FLORIPA M | C100: 4026 | D100: FLP-CONV-ILHA | E100: 172567 | F100: AUTO POSTO SIQUEIRA EIRELI | G100: Sex | H100: 46178
B101: FLORIPA M | C101: 4026 | D101: FLP-CONV-ILHA | E101: 172716 | F101: LANCHONETE ISABELA LTDA | G101: Seg | H101: 46174 | I101: 1
B102: FLORIPA M | C102: 4026 | D102: FLP-CONV-ILHA | E102: 172861 | F102: GUILHERME ARAUJO DE SOUZA | G102: Sex | H102: 46171
...
